Workbook
Name NativeTimeline_Criada: #N/A

Sheet Ideias Canceladas
A1: Número | B1: Descrição curta | C1: Status | D1: Enviado por | E1: Categoria | F1: Sub categoria | G1: Criada | H1: Área de trabalho | I1: Atualizado | J1: Atribuído | K1: Grupo de atribuição | L1: Grupo | M1: Motivo do Cancelamento
A2: FB0096684 | B2: coloca o ponto de almoço automático | C2: Cancelado | D2: Julho Silva | E2: Pequena mudança local | F2: Cost (GE, rework) | G2: 45682.48 | H2: 01. JDE CAFES DO BRASIL UNIDADE PIUMHI | I2: 45861.305 | K2: IDEIAS-MELHORIA CONTÍNUA | L2: =_xlfn.XLOOKUP(TAB.cancelada[[#This Row],[Número]],'tabela ideias'!A:A,'tabela ideias'!O:O,"Não encontrado") -> OPERAÇÃO
A3: FB0103691 | B3: mudar câmara fria de lugar | C3: Cancelado | D3: Fabricio Brant | E3: Pequena mudança local | F3: Safety - Health | G3: 45747.209 | H3: 01. LINHA 01 | I3: 45861.471 | K3: IDEIAS-VACUO | L3: =_xlfn.XLOOKUP(TAB.cancelada[[#This Row],[Número]],'tabela ideias'!A:A,'tabela ideias'!O:O,"Não encontrado") -> OPERAÇÃO
A4: FB0104140 | B4: Peneira vibratória para moega de reprocesso da moagem | C4: Cancelado | D4: Pedro Ferreira | E4: Pequena mudança local | F4: Processo | G4: 45750.48 | H4: 03. MOAGEM | I4: 45959.387 | K4: IDEIAS-PROCESSOS | L4: =_xlfn.XLOOKUP(TAB.cancelada[[#This Row],[Número]],'tabela ideias'!A:A,'tabela ideias'!O:O,"Não encontrado") -> ADM/TÉCNICO/ASSISTENTE/ESTAG.
A5: FB0106437 | B5: criar ponto superior de tomada para o ventilador | C5: Cancelado | D5: Weverton Medeiro | E5: Pequena mudança local | F5: Safety - Health | G5: 45773.69 | H5: 05. LINHA 05 | I5: 45959.474 | K5: IDEIAS-ALMOFADA | L5: =_xlfn.XLOOKUP(TAB.cancelada[[#This Row],[Número]],'tabela ideias'!A:A,'tabela ideias'!O:O,"Não encontrado") -> OPERAÇÃO
A6: FB0106984 | B6: Sensor de presença | C6: Cancelado | D6: Vitor Xavier | E6: Pequena mudança local | F6: Processo | G6: 45778.083 | H6: 07. LINHA 07 | I6: 45852.479 | K6: IDEIAS-PROCESSOS | L6: =_xlfn.XLOOKUP(TAB.cancelada[[#This Row],[Número]],'tabela ideias'!A:A,'tabela ideias'!O:O,"Não encontrado") -> OPERAÇÃO
A7: FB0107019 | B7: Peneira vibratória para moega de reprocesso da moagem | C7: Cancelado | D7: Pedro Ferreira | E7: Pequena mudança local | F7: Processo | G7: 45778.453 | H7: 01. MOINHO 01 | I7: 45939.578 | K7: IDEIAS-PROCESSOS | L7: =_xlfn.XLOOKUP(TAB.cancelada[[#This Row],[Número]],'tabela ideias'!A:A,'tabela ideias'!O:O,"Não encontrado") -> ADM/TÉCNICO/ASSISTENTE/ESTAG.
A8: FB0107098 | B8: Uma das bombas de vácuo , desliga com frequência | C8: Cancelado | D8: Romilda Cunha | E8: Pequena mudança local | F8: Cost (GE, rework) | G8: 45779.737 | H8: 01. LINHA 01 | I8: 45861.471 | K8: IDEIAS-VACUO | L8: =_xlfn.XLOOKUP(TAB.cancelada[[#This Row],[Número]],'tabela ideias'!A:A,'tabela ideias'!O:O,"Não encontrado") -> OPERAÇÃO
A9: FB0115697 | B9: obter algum carrinho ou algo para ajudar virar os tambores de rejeitos na caçamba | C9: Cancelado | D9: Ruth Alves | E9: Pequena mudança local | F9: Safety - Health | G9: 45862.095 | H9: 04. EMPACOTAMENTO | I9: 45933.429 | K9: IDEIAS-ALMOFADA | L9: =_xlfn.XLOOKUP(TAB.cancelada[[#This Row],[Número]],'tabela ideias'!A:A,'tabela ideias'!O:O,"Não encontrado") -> OPERAÇÃO
A10: FB0116922 | B10: na PKD não tem um acessório específico para apertar as aparas . | C10: Cancelado | D10: Angela Santos | E10: Pequena mudança local | F10: Qualidade | G10: 45874.238 | H10: 05. LINHA 05 | I10: 45960.371 | K10: IDEIAS-ALMOFADA | L10: =_xlfn.XLOOKUP(TAB.cancelada[[#This Row],[Número]],'tabela ideias'!A:A,'tabela ideias'!O:O,"Não encontrado") -> OPERAÇÃO
A11: FB0107079 | B11: manômetro de pressão | C11: Cancelado | D11: Sara Lobato | E11: Pequena mudança local | F11: Processo | G11: 45779.472 | H11: 05. LINHA 05 | I11: 45945.348 | J11: Relton Moraes | K11: IDEIAS-ALMOFADA | L11: =_xlfn.XLOOKUP(TAB.cancelada[[#This Row],[Número]],'tabela ideias'!A:A,'tabela ideias'!O:O,"Não encontrado") -> OPERAÇÃO
A12: FB0122221 | B12: Suporte | C12: Cancelado | D12: Vitor Xavier | E12: Pequena mudança local | F12: Organisation of work | L12: =_xlfn.XLOOKUP(TAB.cancelada[[#This Row],[Número]],'tabela ideias'!A:A,'tabela ideias'!O:O,"Não encontrado") -> OPERAÇÃO
A13: FB0131366 | B13: ter um suporte com uma placa informando qual café está moendo nos moinhos que tem as moegas. | C13: Cancelado | D13: Ruth Fonseca | E13: Pequena mudança local | F13: Qualidade | G13: 46002.964 | H13: 04. EMPACOTAMENTO | I13: 46224.687 | J13: Angelina Destefani | K13: APROVADORES DE IDEIAS | L13: =_xlfn.XLOOKUP(TAB.cancelada[[#This Row],[Número]],'tabela ideias'!A:A,'tabela ideias'!O:O,"Não encontrado") -> OPERAÇÃO
A14: FB0100188 | B14: instalar botoeira de emergencia na esteira do zero hora | C14: Cancelado | E14: Pequena mudança local | F14: Safety - Health | G14: 45714.34 | H14: 01. LINHA 01 | I14: 46276.538 | J14: Andre Mendes Costa | K14: APROVADORES DE IDEIAS | L14: =_xlfn.XLOOKUP(TAB.cancelada[[#This Row],[Número]],'tabela ideias'!A:A,'tabela ideias'!O:O,"Não encontrado") -> 0
A15: FB0110676 | B15: Compra de micrômetro. | C15: Cancelado | D15: Douglas Destefani | E15: Pequena mudança local | F15: Qualidade | G15: 45813.52 | H15: 09.16 Qualidade CQ | I15: 46276.554 | J15: Tais Costa | K15: APROVADORES DE IDEIAS | L15: =_xlfn.XLOOKUP(TAB.cancelada[[#This Row],[Número]],'tabela ideias'!A:A,'tabela ideias'!O:O,"Não encontrado") -> OPERAÇÃO
A16: FB0119798 | B16: correias das Raumak e fabrimas | C16: Cancelado | D16: Thais Souza | E16: Pequena mudança local | F16: Processo | G16: 45903.654 | H16: 05. LINHA 05 | I16: 46276.586 | J16: Ana Martins | K16: APROVADORES DE IDEIAS | L16: =_xlfn.XLOOKUP(TAB.cancelada[[#This Row],[Número]],'tabela ideias'!A:A,'tabela ideias'!O:O,"Não encontrado") -> OPERAÇÃO
A17: FB0104724 | B17: elevador de canecas 1 e 3 está com vazamento de café | C17: Cancelado | D17: Alex Teixeira | E17: Pequena mudança local | F17: Organisation of work | G17: 45756.75 | H17: 03. MOAGEM | I17: 46188.573 | J17: Anderson Santana | K17: IDEIAS-PROCESSOS | L17: =_xlfn.XLOOKUP(TAB.cancelada[[#This Row],[Número]],'tabela ideias'!A:A,'tabela ideias'!O:O,"Não encontrado") -> OPERAÇÃO
A18: FB0138051 | B18: fazer um claviculário de segurança com as chaves das escadas marinheiro no alarme de incêndio | C18: Cancelado | D18: Arthur Silva | E18: Pequena mudança local | F18: Safety - Health | G18: 46064.582 | H18: 09.19 SALA DE PRODUTOS QUÍMICOS | I18: 46098.651 | K18: IDEIAS-SHE | L18: =_xlfn.XLOOKUP(TAB.cancelada[[#This Row],[Número]],'tabela ideias'!A:A,'tabela ideias'!O:O,"Não encontrado") -> ADM/TÉCNICO/ASSISTENTE/ESTAG.
A19: FB0128543 | B19: Sistema de segurança rosca película | C19: Cancelado | D19: Moises Costa | E19: Pequena mudança local | F19: Cost (GE, rework) | G19: 45980.398 | H19: 02. TORREFAÇÃO | I19: 46143.553 | K19: IDEIAS-PROCESSOS | L19: =_xlfn.XLOOKUP(TAB.cancelada[[#This Row],[Número]],'tabela ideias'!A:A,'tabela ideias'!O:O,"Não encontrado") -> OPERAÇÃO
A20: FB0114559 | B20: acesso a parte superior dos silos | C20: Cancelado | D20: Valdeci Simoes | E20: Pequena mudança local | F20: Organisation of work | G20: 45849.872 | H20: 09.19 SALA DE PRODUTOS QUÍMICOS | I20: 46120.703 | K20: IDEIAS-SHE | L20: =_xlfn.XLOOKUP(TAB.cancelada[[#This Row],[Número]],'tabela ideias'!A:A,'tabela ideias'!O:O,"Não encontrado") -> OPERAÇÃO
A21: FB0143304 | B21: Solicitação de isenção da taxa de lixo junto à prefeitura, considerando que a empresa realiza descarte de resíduos por empresa especializada. | C21: Cancelado | D21: Ana Pereira | E21: Pequena mudança local | F21: Cost (GE, rework) | G21: 46107.547 | H21: 06. ADMINISTRATIVO | I21: 46205.597 | J21: Samuel Camargos | K21: APROVADORES DE IDEIAS | L21: =_xlfn.XLOOKUP(TAB.cancelada[[#This Row],[Número]],'tabela ideias'!A:A,'tabela ideias'!O:O,"Não encontrado") -> ADM/TÉCNICO/ASSISTENTE/ESTAG.
A22: FB0088501 | B22: Melhoria no óculos de segurança | C22: Cancelado | D22: Edvaldo Silva | E22: Pequena mudança local | F22: Safety - Health | G22: 45608.788 | H22: 09.19 SALA DE PRODUTOS QUÍMICOS | I22: 46099.4 | K22: IDEIAS-SHE | L22: =_xlfn.XLOOKUP(TAB.cancelada[[#This Row],[Número]],'tabela ideias'!A:A,'tabela ideias'!O:O,"Não encontrado") -> OPERAÇÃO
A23: FB0132034 | B23: Inclusão de atividade no CIL | C23: Cancelado | D23: Relton Moraes | E23: Pequena mudança local | F23: Processo | G23: 46008.632 | H23: 04. EMPACOTAMENTO | I23: 46156.618 | J23: Bianca Silva | K23: APROVADORES DE IDEIAS | L23: =_xlfn.XLOOKUP(TAB.cancelada[[#This Row],[Número]],'tabela ideias'!A:A,'tabela ideias'!O:O,"Não encontrado") -> ADM/TÉCNICO/ASSISTENTE/ESTAG.
A24: FB0102939 | B24: TREINAMENTO SCRIPT | C24: Cancelado | D24: Aline Fernandes | E24: Pequena mudança local | F24: Organisation of work | G24: 45740.636 | H24: 01. JDE CAFES DO BRASIL UNIDADE PIUMHI | I24: 46170.51 | J24: Luzia Rodrigues | K24: IDEIAS-MELHORIA CONTÍNUA | L24: =_xlfn.XLOOKUP(TAB.cancelada[[#This Row],[Número]],'tabela ideias'!A:A,'tabela ideias'!O:O,"Não encontrado") -> ADM/TÉCNICO/ASSISTENTE/ESTAG.
A25: FB0139843 | B25: facilita o acesso aos bojos sem a necessidade de PT | C25: Cancelado | D25: Alex Teixeira | E25: Grande mudança local | F25: Safety - Health | G25: 46080.341 | H25: 03. MOAGEM | I25: 46132.764 | K25: IDEIAS-PROCESSOS | L25: =_xlfn.XLOOKUP(TAB.cancelada[[#This Row],[Número]],'tabela ideias'!A:A,'tabela ideias'!O:O,"Não encontrado") -> OPERAÇÃO
A26: FB0125662 | B26: Criar instruções para as sirenes das Fabrimas (troca de Silo) | C26: Cancelado | D26: Pedro Ferreira | E26: Pequena mudança local | F26: Cost (GE, rework) | G26: 45957.475 | H26: 04. EMPACOTAMENTO | I26: 46156.666 | K26: APROVADORES DE IDEIAS | L26: =_xlfn.XLOOKUP(TAB.cancelada[[#This Row],[Número]],'tabela ideias'!A:A,'tabela ideias'!O:O,"Não encontrado") -> ADM/TÉCNICO/ASSISTENTE/ESTAG.
A27: FB0124354 | B27: Manual com imagens e passos para a inserção da bobina na fabrima | C27: Cancelado | D27: Valeria Yanez | E27: Pequena mudança local | F27: Organisation of work | G27: 45945.413 | H27: 04. EMPACOTAMENTO | I27: 46156.633 | J27: Tais Costa | K27: APROVADORES DE IDEIAS | L27: =_xlfn.XLOOKUP(TAB.cancelada[[#This Row],[Número]],'tabela ideias'!A:A,'tabela ideias'!O:O,"Não encontrado") -> ADM/TÉCNICO/ASSISTENTE/ESTAG.
A28: FB0147886 | B28: colocar uma tomada nesse local | C28: Cancelado | D28: Luiz H Silva | E28: Pequena mudança local | F28: Organisation of work | G28: 46141.31 | H28: 03. MOAGEM | I28: 46237.432 | J28: Ana Martins | K28: APROVADORES DE IDEIAS | L28: =_xlfn.XLOOKUP(TAB.cancelada[[#This Row],[Número]],'tabela ideias'!A:A,'tabela ideias'!O:O,"Não encontrado") -> OPERAÇÃO
A29: FB0154914 | B29: Substituição dos sensores magnéticos das portas por modelos com LED de indicação visual, facilitando a identificação de portas abertas, mal fechadas ou sensores | C29: Cancelado | D29: Igor Sousa | E29: Grande mudança local | F29: Product | G29: 46188.623 | H29: 01. JDE CAFES DO BRASIL UNIDADE PIUMHI | I29: 46192.456 | K29: IDEIAS-MELHORIA CONTÍNUA | L29: =_xlfn.XLOOKUP(TAB.cancelada[[#This Row],[Número]],'tabela ideias'!A:A,'tabela ideias'!O:O,"Não encontrado") -> ADM/TÉCNICO/ASSISTENTE/ESTAG.
A30: FB0086839 | B30: Ligação independente para codificadora de caixas | C30: Cancelado | D30: Michelle Faria | E30: Pequena mudança local | F30: Processo | G30: 45594.157 | H30: 01. LINHA 01 | I30: 45859.447 | J30: Igor Sousa | K30: IDEIAS-VACUO | L30: =_xlfn.XLOOKUP(TAB.cancelada[[#This Row],[Número]],'tabela ideias'!A:A,'tabela ideias'!O:O,"Não encontrado") -> ADM/TÉCNICO/ASSISTENTE/ESTAG.
A31: FB0087245 | B31: colocar as limpeza t3 cil | C31: Cancelado | D31: Julho Silva | E31: Pequena mudança local | F31: Qualidade | G31: 45596.582 | H31: 02. TORREFAÇÃO | I31: 45811.457 | J31: Priscilla Araujo | K31: IDEIAS-PROCESSOS | L31: =_xlfn.XLOOKUP(TAB.cancelada[[#This Row],[Número]],'tabela ideias'!A:A,'tabela ideias'!O:O,"Não encontrado") -> OPERAÇÃO

Sheet tabela ideias
A1: Número | B1: Descrição curta | C1: Status | D1: Descrição | E1: Enviado por | F1: Categoria | G1: Sub categoria | H1: Criada | I1: Área de trabalho | J1: Atualizado | K1: Atribuído a | L1: Grupo de atribuição | M1: Fechado | N1: Status controle interno | O1: Grupo | P1: canceladas
A2: FB0076323 | B2: Escada dando acesso aos Detectores de Metais | C2: Cancelado | D2: Uma Escada facilitando o acesso aos Detectores de Metais do lado da Fabrima 05 | E2: Isaias Macedo | F2: Pequena mudança local | G2: Organisation of work | H2: 45506.412 | I2: 04. EMPACOTAMENTO | J2: 45552.653 | L2: APROVADORES DE IDEIAS | M2: 45552.653 | N2: Cancelado | O2: =_xlfn.XLOOKUP(TAB.IDEIAS.TOTAL[[#This Row],[Enviado por]],'BASE DMOS'!A:A,'BASE DMOS'!C:C,"Não encontrado") -> OPERAÇÃO | P2: Cancelada
A3: FB0076530 | B3: Isolamento do Vão da Escada Mesanino PKD | C3: Fechado | D3: Devido ao no leaut dos contêiner foi necessário retirar um móvel que havia debaixo do vão da escada ficando um local aberto possibilitando a passagem por baixo da escada em um ponto onde existe a possibilidade de colisão com o rosto ou cabeça. Devido. a necessidade de isolamento podemos aproveitar essa espaço com um armário um com suporte para um bebedouro, e a guarda de utensílios. | E3: Patrick Pessoa | F3: Pequena mudança local | G3: Safety - Health | H3: 45509.402 | I3: 01. LINHA 01 | J3: 45839.432 | K3: Bianca Silva | L3: IDEIAS-VACUO | M3: 45839.432 | N3: Fechado | O3: =_xlfn.XLOOKUP(TAB.IDEIAS.TOTAL[[#This Row],[Enviado por]],'BASE DMOS'!A:A,'BASE DMOS'!C:C,"Não encontrado") -> OPERAÇÃO
A4: FB0076596 | B4: Avaliar relatório de inspeção do ciclones de cinza e película se é pra inspecionar ou retira da folhas o formulários… | C4: Resolvido | D4: Hoje não e feito a inspeção de cinza e película do relatório(FRM-07-016) foi feito uma melhoria colocando sensor de presença na rosca atuando alarme no supervisório quando a caçamba de película está cheia …. Sugiro que seja retirado esta página | E4: Edvan Santos | F4: Pequena mudança local | G4: Processo | H4: 45510.23 | I4: 02. TORREFAÇÃO | J4: 46142.688 | K4: Tiago Carvalho | L4: IDEIAS-PROCESSOS | N4: Resolvido | O4: =_xlfn.XLOOKUP(TAB.IDEIAS.TOTAL[[#This Row],[Enviado por]],'BASE DMOS'!A:A,'BASE DMOS'!C:C,"Não encontrado") -> OPERAÇÃO
A5: FB0076597 | B5: moega de reprocesso e dosagem de café | C5: Cancelado | D5: Moega de reprocesso e dosagem e um processo de melhorar e facilitar o reprocesso de café dos turnos agilizando toda etapa do café para seu devido silo de pó. Para esta melhoria seria utilizado algumas peças que estão obsoletas da linha de grãos e da extratora antiga. | E5: Luiz H Silva | F5: Pequena mudança local | G5: Processo | H5: 45510.246 | I5: 03. MOAGEM | J5: 46140.566 | L5: IDEIAS-PROCESSOS | M5: 46140.566 | N5: Cancelado | O5: =_xlfn.XLOOKUP(TAB.IDEIAS.TOTAL[[#This Row],[Enviado por]],'BASE DMOS'!A:A,'BASE DMOS'!C:C,"Não encontrado") -> OPERAÇÃO
A6: FB0076655 | B6: mesa de pacotes para analise | C6: Fechado | D6: Realizar a confecção de um adesivo referente as numerações das câmaras de vácuo e colocar na mesa de recolhimento de pacotes para análise para posicionamento dos pacotes referente a cada câmara . O adesivo deverá ser confeccionado com impressão da direita para esquerda para acompanhar a forma que pacote sai da roda de vácuo e com é retirado pelos operadores Da seguinte forma de 1 a 4 de 5 a 8 é demais na sequencia até finalizar as 28 câmaras Os pacotes são retirados de 4 a 4 por vez. Pedro Ferreira: Ideia realizada, porém, falta o operador colar os adesivos na mesa. | E6: Patrick Pessoa | F6: Pequena mudança local | G6: Qualidade | H6: 45510.603 | I6: 01. LINHA 01 | J6: 45901.481 | K6: Bianca Silva | L6: IDEIAS-VACUO | M6: 45901.481 | N6: Fechado | O6: =_xlfn.XLOOKUP(TAB.IDEIAS.TOTAL[[#This Row],[Enviado por]],'BASE DMOS'!A:A,'BASE DMOS'!C:C,"Não encontrado") -> OPERAÇÃO
A7: FB0076876 | B7: Claviculário almoxarifado | C7: Fechado | D7: Colocar claviculário com todas as chaves dos armários e portões do almoxarifado numeradas e em ordem, para restringir acesso aos materiais. | E7: Sarah Teixeira | F7: Pequena mudança local | G7: Organisation of work | H7: 45512.688 | I7: 09.1 ALMOXARIFADO | J7: 45523.563 | K7: Sarah Teixeira | L7: IDEIAS-CAFÉ CRÚ | M7: 45523.563 | N7: Fechado | O7: =_xlfn.XLOOKUP(TAB.IDEIAS.TOTAL[[#This Row],[Enviado por]],'BASE DMOS'!A:A,'BASE DMOS'!C:C,"Não encontrado") -> ADM/TÉCNICO/ASSISTENTE/ESTAG.
A8: FB0076877 | B8: Criação de Forms para registro de saídas de almoxarifado | C8: Fechado | D8: Criação de Forms para registro de saídas de almoxarifado, facilitando para quem precisa retirar materiais quando não tem almoxarife para fazer os registros. | E8: Sarah Teixeira | F8: Pequena mudança local | G8: Organisation of work | H8: 45512.694 | I8: 09.1 ALMOXARIFADO | J8: 45527.625 | K8: Sarah Teixeira | L8: IDEIAS-CAFÉ CRÚ | M8: 45527.625 | N8: Fechado | O8: =_xlfn.XLOOKUP(TAB.IDEIAS.TOTAL[[#This Row],[Enviado por]],'BASE DMOS'!A:A,'BASE DMOS'!C:C,"Não encontrado") -> ADM/TÉCNICO/ASSISTENTE/ESTAG. | P8: cancela
A9: FB0076880 | B9: Suporte para etiquetas de fardo | C9: Fechado | D9: Colocar um suporte para colocar as etiquetas dos fardos na parede do CQ, trazer as etiquetas para mais próximo ao almoxarifado e organizar melhor | E9: Sarah Teixeira | F9: Pequena mudança local | G9: Organisation of work | H9: 45512.704 | I9: 09.1 ALMOXARIFADO | J9: 45639.63 | K9: Sarah Teixeira | L9: IDEIAS-CAFÉ CRÚ | M9: 45639.63 | N9: Fechado | O9: =_xlfn.XLOOKUP(TAB.IDEIAS.TOTAL[[#This Row],[Enviado por]],'BASE DMOS'!A:A,'BASE DMOS'!C:C,"Não encontrado") -> ADM/TÉCNICO/ASSISTENTE/ESTAG.
A10: FB0076937 | B10: Retornar com os Teclados e Mouse sem fio | C10: Cancelado | D10: Retornar Mouse e Teclados sem fio,para facilitar o uso sem precisar utilizar suporte para Mouse e não ocupar tanto espaço na mesa | E10: Isaias Macedo | F10: Pequena mudança local | G10: Organisation of work | H10: 45513.305 | I10: 04. LINHA 04 | J10: 45769.669 | L10: APROVADORES DE IDEIAS | M10: 45769.669 | N10: Cancelado | O10: =_xlfn.XLOOKUP(TAB.IDEIAS.TOTAL[[#This Row],[Enviado por]],'BASE DMOS'!A:A,'BASE DMOS'!C:C,"Não encontrado") -> OPERAÇÃO
A11: FB0076944 | B11: Mola Aérea Para Fechamento De Portas Automática - Almoxarifado | C11: Fechado | D11: Colocar uma Mola Aérea Para Fechamento De Portas Automática nas portas do almoxarifado, o fluxo de mecânicos é muito grande e deixam a porta aberta ao sair, se fazendo necessário parar as atividades para fechar a porta. | E11: Sarah Teixeira | F11: Pequena mudança local | G11: Safety - Health | H11: 45513.343 | I11: 09.1 ALMOXARIFADO | J11: 45531.609 | K11: Sarah Teixeira | L11: IDEIAS-CAFÉ CRÚ | M11: 45531.609 | N11: Fechado | O11: =_xlfn.XLOOKUP(TAB.IDEIAS.TOTAL[[#This Row],[Enviado por]],'BASE DMOS'!A:A,'BASE DMOS'!C:C,"Não encontrado") -> ADM/TÉCNICO/ASSISTENTE/ESTAG.
A12: FB0077045 | B12: aplicativo de RO | C12: Resolvido | D12: Colocar uma opção de fotografia no aplicativo de RO para melhor visualização da ocorrência, assim o reporte ficará mais claro pra as pessoas que irão conduzir uma RCA, trazendo uma transparência no que de fato ocorreu e agilidade na tratativa para que seja discutido em OPS. | E12: Edvan Santos | F12: Pequena mudança local | G12: Qualidade | H12: 45516.215 | I12: 09.16 Qualidade CQ | J12: 45807.392 | L12: IDEIAS-QUALIDADE | N12: Resolvido | O12: =_xlfn.XLOOKUP(TAB.IDEIAS.TOTAL[[#This Row],[Enviado por]],'BASE DMOS'!A:A,'BASE DMOS'!C:C,"Não encontrado") -> OPERAÇÃO
A13: FB0077070 | B13: Caixa box não abre | C13: Em andamento | D13: Realizar um sistema de parada na encaixotadora . Caso a caixa box venha colada no interior ela não abre com isso o sensor de parada do magazine não atua e com isso ela passa fechada e com isso fica enroscada nas guias de fechamento da abas laterais com essa falha ocorre o amassamento de pacotes da caixa que vem subsequente ocorrendo perda de pacotes e caixas é risco de quebra do equipamento o esforço ou soltar a corrente principal . OBS Ideia já foi discutida com Igor da Programação. Ana, por favor, programar com o Igor/Eliezer, para realização. | E13: Patrick Pessoa | F13: Pequena mudança local | G13: Cost (GE, rework) | H13: 45516.386 | I13: 01. LINHA 01 | J13: 46202.758 | K13: Ana Martins | L13: APROVADORES DE IDEIAS | N13: Aguardando Execução | O13: =_xlfn.XLOOKUP(TAB.IDEIAS.TOTAL[[#This Row],[Enviado por]],'BASE DMOS'!A:A,'BASE DMOS'!C:C,"Não encontrado") -> OPERAÇÃO
A14: FB0077079 | B14: Sistema Alarme Sonoro e Luminoso | C14: Fechado | D14: Necessidade de colocar um sistema de alarme Sonoro e luminoso no sistema da encaixotadora . Que o momento que ocorrer a falha ele alerte os operadores caso eles estejam desempenhando outra atividade no momento da falha. OBS Ideia discutida com Igor Programação | E14: Patrick Pessoa | F14: Pequena mudança local | G14: Cost (GE, rework) | H14: 45516.398 | I14: 01. LINHA 01 | J14: 45839.432 | K14: Igor Sousa | L14: IDEIAS-VACUO | M14: 45839.432 | N14: Fechado | O14: =_xlfn.XLOOKUP(TAB.IDEIAS.TOTAL[[#This Row],[Enviado por]],'BASE DMOS'!A:A,'BASE DMOS'!C:C,"Não encontrado") -> OPERAÇÃO
A15: FB0077133 | B15: Código de parada alarme de incêndio | C15: Cancelado | D15: Criar um código de parada para quando o brigadista precisar se ausentar da máquina devido ao acionamento do alarme e houver intercorrência e não tiver ninguém para reveza-lo no momento. | E15: Vinicius De Oliveira | F15: Pequena mudança local | G15: Cost (GE, rework) | H15: 45517.006 | I15: 05. LINHA 05 | J15: 45551.689 | L15: APROVADORES DE IDEIAS | M15: 45551.689 | N15: Cancelado | O15: =_xlfn.XLOOKUP(TAB.IDEIAS.TOTAL[[#This Row],[Enviado por]],'BASE DMOS'!A:A,'BASE DMOS'!C:C,"Não encontrado") -> OPERAÇÃO
A16: FB0077202 | B16: abridor de abas encaixotadora | C16: Fechado | D16: Foi realizada nova confecção de abridores de aba , com ângulo de 45 graus para melhorar abertura da caixa , assim voltando com as condições da máquina de base. Protótipo está em funcionamento feito do material de acrílico e estando com bons resultados na máquina. Participantes . Wesley,Patrick,Arthur,Mário rizo | E16: Wesley J Silva | F16: Pequena mudança local | G16: Cost (GE, rework) | H16: 45517.36 | I16: 01. LINHA 01 | J16: 45594.547 | L16: IDEIAS-VACUO | M16: 45594.547 | N16: Fechado | O16: =_xlfn.XLOOKUP(TAB.IDEIAS.TOTAL[[#This Row],[Enviado por]],'BASE DMOS'!A:A,'BASE DMOS'!C:C,"Não encontrado") -> OPERAÇÃO
A17: FB0077203 | B17: Expulsador de caixa box | C17: Fechado | D17: Realizar o desenvolvimento de acionamento manual no expulsador da balança de peso. Para quando ocorre pequena falha no robô o operador possa utilizar o acionamento manual para expulsar caixa sem que haja parada de máquina. Ideia: Discutida com Igor Santos Programação , Realmente é uma ótima ideia, porém todo circuito de NR12 esta interligado com o robô para ser realizado precisa a trazer uma empresa autorizada em NR12 e refazer todo circuito de NR12 novamente para que isso seja concretizado. | E17: Patrick Pessoa | F17: Pequena mudança local | G17: Cost (GE, rework) | H17: 45517.376 | I17: 01. LINHA 01 | J17: 45842.422 | K17: Igor Sousa | L17: IDEIAS-VACUO | M17: 45842.422 | N17: Fechado | O17: =_xlfn.XLOOKUP(TAB.IDEIAS.TOTAL[[#This Row],[Enviado por]],'BASE DMOS'!A:A,'BASE DMOS'!C:C,"Não encontrado") -> OPERAÇÃO
A18: FB0077256 | B18: tambores de capitação de pó filtro de mangas do despredador 1 | C18: Em andamento | D18: Os tambores de capitação de pó do filtro de mangas do despredador 1 estão vazando muito pó porque eles não possuem travas e existe outros tambores que possuem travas e estão desativados porque eram do despredador 2 e hoje não funciona mais, aí poderiam ser substituídos | E18: Valdeci Simoes | F18: Pequena mudança local | G18: Safety - Health | H18: 45518.075 | I18: 01. CAFÉ CRU | J18: 45526.451 | K18: Caique Ventura | L18: IDEIAS-CAFÉ CRÚ | N18: Aguardando Execução | O18: =_xlfn.XLOOKUP(TAB.IDEIAS.TOTAL[[#This Row],[Enviado por]],'BASE DMOS'!A:A,'BASE DMOS'!C:C,"Não encontrado") -> OPERAÇÃO
A19: FB0077257 | B19: suporte de proteção da moega onde joga bags | C19: Resolvido | D19: O novo sistema de entrada de café em bags não possui proteção, podendo amassar a estrutura da moega quando for jogar bag | E19: Valdeci Simoes | F19: Pequena mudança local | G19: Processo | H19: 45518.079 | I19: 01. CAFÉ CRU | J19: 46210.502 | K19: Ruth Alves | L19: APROVADORES DE IDEIAS | N19: Resolvido | O19: =_xlfn.XLOOKUP(TAB.IDEIAS.TOTAL[[#This Row],[Enviado por]],'BASE DMOS'!A:A,'BASE DMOS'!C:C,"Não encontrado") -> OPERAÇÃO
A20: FB0077258 | B20: Tomadas 220 | C20: Em andamento | D20: Colocar pontos de tomada 220 em cima dos silos de grão e pó. Eliézer: é possivel instalar as tomadas porem não temos recursos internos para isso, @leonardo por favor puxar orçamento com Mateus Eletromarzinho | E20: Leonardo Junior | F20: Pequena mudança local | G20: Energy efficiency | H20: 45518.12 | I20: 14. SILOS CAFE MOIDO | J20: 45960.603 | K20: Ana Martins | L20: IDEIAS-PROCESSOS | N20: Aguardando Aprovação de CAPEX | O20: =_xlfn.XLOOKUP(TAB.IDEIAS.TOTAL[[#This Row],[Enviado por]],'BASE DMOS'!A:A,'BASE DMOS'!C:C,"Não encontrado") -> OPERAÇÃO
A21: FB0077552 | B21: descer as válvula de água para baixo | C21: Fechado | D21: A procedimento em desligar o torrador tendo que fecha as válvula do tanque de água ,ao ligar também sendo assim acesso o tanque devido a escada marinheiro precisar fazer pt e wlmra é gera um tempo acha as pessoa responsável para assinar o documento, descendo as válvula para baixo o tempo que gastaria para fazer o documento ganharia em produtividade | E21: Julho Silva | F21: Pequena mudança local | G21: Processo | H21: 45520.408 | I21: 02. TORREFAÇÃO | J21: 45862.592 | K21: Igor Sousa | L21: IDEIAS-PROCESSOS | M21: 45862.592 | N21: Fechado | O21: =_xlfn.XLOOKUP(TAB.IDEIAS.TOTAL[[#This Row],[Enviado por]],'BASE DMOS'!A:A,'BASE DMOS'!C:C,"Não encontrado") -> OPERAÇÃO
A22: FB0077563 | B22: Redução de carreta no pátio | C22: Fechado | D22: Deixar entrar as carretas que estão programadas para descarregar no turno para tirar amostra e não todas do dia as 6h como é hoje. Será necessário priorizar a atividade de tirar amostra logo após contagem de estoque, para não correr risco de atrasos no CQCV. Teremos no máximo 3 carretas no pátio, o que ajuda o almoxarifado ao descarregar cavaco, facilita na gestão de estoque e demais movimentações, além da divisão de atividades entre turnos sobrará tempo para jogar bags e outras atividades no 1 turno | E22: Nilton F Costa | F22: Pequena mudança local | G22: Organisation of work | H22: 45520.483 | I22: 01. CAFÉ CRU | J22: 45595.358 | K22: Sarah Teixeira | L22: IDEIAS-CAFÉ CRÚ | M22: 45595.358 | N22: Fechado | O22: =_xlfn.XLOOKUP(TAB.IDEIAS.TOTAL[[#This Row],[Enviado por]],'BASE DMOS'!A:A,'BASE DMOS'!C:C,"Não encontrado") -> OPERAÇÃO
A23: FB0077783 | B23: Cantoneira para fixar cortina | C23: Cancelado | D23: Seria necessário fixar uma cantoneira para fixação da cortina. Pois toda vez que uma carreta entra na plataforma é preciso segurar parte da cortina para o motorista enxergar a faixa amarela que o auxilia no alinhamento dos pneus da carreta. | E23: Jose Junior | F23: Pequena mudança local | G23: Safety - Health | H23: 45523.728 | I23: 08. LOGISTICA | J23: 45771.477 | L23: IDEIAS-LOGÍSTICA | M23: 45771.477 | N23: Cancelado | O23: =_xlfn.XLOOKUP(TAB.IDEIAS.TOTAL[[#This Row],[Enviado por]],'BASE DMOS'!A:A,'BASE DMOS'!C:C,"Não encontrado") -> OPERAÇÃO
A24: FB0077784 | B24: Sistema de ventilação e exaustão | C24: Em andamento | D24: Nesta área de recebimento das carretas,ao entrar nelas não existe um sistema de circulação de ar,ou exaustor para captar o pó na descarga do café. A falta de uma ventilação eficiente prejudica a respiração e exaustão do corpo,fazendo o operador a suar excessivamente,causando desidratação. SHE: Hiago, o conforto térmico não esta conectado com o projeto ATEX. Eles podem ser desenvolvido juntos mas os objetivos são diferentes. É possivel realizar melhorias na aclimatação do setor. Deevemos fazer uma MOC e na sequencia abrir uma TAP. Do ponto de vista de SHE a ideia está aprovada. | E24: Jose Junior | F24: Pequena mudança local | G24: Safety - Health | H24: 45523.734 | I24: 01. CAFÉ CRU | J24: 46132.775 | K24: Tiago Carvalho | L24: IDEIAS-CAFÉ CRÚ | N24: Aguardando MOC | O24: =_xlfn.XLOOKUP(TAB.IDEIAS.TOTAL[[#This Row],[Enviado por]],'BASE DMOS'!A:A,'BASE DMOS'!C:C,"Não encontrado") -> OPERAÇÃO
A25: FB0078291 | B25: Aumento de capacidade de estoque de café cru | C25: Fechado | D25: Atualmente armazenamos 1000kg de café em cada bag, com isso sobra um espaço vazio em cada bag. A proposta é aumentar para 1100kg em cada bag, respeitando sua capacidade máxima de armazenamento. Solicitar ao Michel EGE para configurar a quantidade de café na retirada de bag. | E25: Nilton F Costa | F25: Pequena mudança local | G25: Organisation of work | H25: 45527.302 | I25: 01. CAFÉ CRU | J25: 45639.628 | K25: Sarah Teixeira | L25: IDEIAS-CAFÉ CRÚ | M25: 45639.628 | N25: Fechado | O25: =_xlfn.XLOOKUP(TAB.IDEIAS.TOTAL[[#This Row],[Enviado por]],'BASE DMOS'!A:A,'BASE DMOS'!C:C,"Não encontrado") -> OPERAÇÃO
A26: FB0078586 | B26: fechador de abas | C26: Fechado | D26: confecção de um nomo modelo de fechador de abas para encaixotadora mais simples e eficaz | E26: Arthur Silva | F26: Pequena mudança local | G26: Product | H26: 45530.475 | I26: 01. LINHA 01 | J26: 45594.58 | L26: IDEIAS-VACUO | M26: 45594.58 | N26: Fechado | O26: =_xlfn.XLOOKUP(TAB.IDEIAS.TOTAL[[#This Row],[Enviado por]],'BASE DMOS'!A:A,'BASE DMOS'!C:C,"Não encontrado") -> ADM/TÉCNICO/ASSISTENTE/ESTAG.
A27: FB0078785 | B27: Programa de apadrinhamento da operação pela manutenção | C27: Em andamento | D27: IDEIA Criar um programa onde os associados que estão fazendo ou já fizeram curso técnico de eletrônico e mecânico sejam apadrinhados pelos manutentores na execução de atividades em paradas e preventivas possibilitando transferência de conhecimento e preparação para próximas oportunidades. --------------------- FEEDBACK Edvan, obrigada pela ideia. Vamos ver como conseguimos incorporar isso integrando o pilar de MA e ORG. A Luzia vai verificar. (Lu, analisar por favor e colocar em pauta para algum desses pilares) FEEDBACK 23/09/2025: Creio que seja uma ótima oportunidade de aprendizado mas que precisará de um plano para garantir oportunidades igualitárias sem que impacte as atividades operacionais e manutenções. Levarei para o pilar Org, creio ser uma frente de trabalho possível para 2026. FEEDBACK 28/05/2026: Atribuindo e encaminhando à Fabrizia para que analise e veja se é possível levar o tema no pilar org ou se não está alinhado a estratégia do momento. | E27: Edvan Santos | F27: Pequena mudança local | G27: Organisation of work | H27: 45532.233 | I27: 01. TORRADORES | J27: 46206.451 | K27: Fabrizia Soares | L27: APROVADORES DE IDEIAS | N27: Aguardando Execução | O27: =_xlfn.XLOOKUP(TAB.IDEIAS.TOTAL[[#This Row],[Enviado por]],'BASE DMOS'!A:A,'BASE DMOS'!C:C,"Não encontrado") -> OPERAÇÃO
A28: FB0081067 | B28: testador de vácuo PKD | C28: Resolvido | D28: O testador de vácuo está amaçando o pacote durante o teste de pressão . Com esse amaçado o pacote ganha uma inclinação vindo a escorregar na encaixotadora e também podendo rasgar a caixa durante o enchimentos devido a forma que fundo do pacote fica. Realizar uma melhoria no stop do testador afim que a chapa que segura o pacote não encline para não amassar o pacote. Ideia discutida com Arthur da manutenção | E28: Patrick Pessoa | F28: Pequena mudança local | G28: Qualidade | H28: 45546.514 | I28: 01. LINHA 01 | J28: 46049.549 | K28: Henrique Cardoso | L28: IDEIAS-VACUO | N28: Resolvido | O28: =_xlfn.XLOOKUP(TAB.IDEIAS.TOTAL[[#This Row],[Enviado por]],'BASE DMOS'!A:A,'BASE DMOS'!C:C,"Não encontrado") -> OPERAÇÃO | P28: CANCELADO
A29: FB0081758 | B29: Substituir as lixeiras sem cor por lixeiras com a cor da soleta seletiva | C29: Cancelado | D29: Por 5S, a sugestão é substituirmos as lixeiras por lixeiras novas nas linhas de acordo com as cores da coleta seletiva (igual tem na logísitca). Elas não ficam encardidas. Não precisa trocar agora, mas na próxima substituição considerar esse modelo. | E29: Giovanna Biffaratte | F29: Pequena mudança local | G29: Organisation of work | H29: 45552.915 | I29: 04. EMPACOTAMENTO | J29: 45770.462 | L29: APROVADORES DE IDEIAS | M29: 45770.462 | N29: Cancelado | O29: =_xlfn.XLOOKUP(TAB.IDEIAS.TOTAL[[#This Row],[Enviado por]],'BASE DMOS'!A:A,'BASE DMOS'!C:C,"Não encontrado") -> ADM/TÉCNICO/ASSISTENTE/ESTAG.
A30: FB0082056 | B30: Plano fixo de Cafés | C30: Cancelado | D30: Fixar o plano de cafés nas fabrimas, onde as fabrimas 4 e 5 produziriam café de canaleta fechada, que é o tipo de café que tem a melhor performance nas máquinas. E as fabrimas 2 e 3 produziriam cafés de canaletas abertas, que é o tipo de café que produz melhor nas máquinas. (Aberto a opiniões) | E30: Rafael Santos | F30: Pequena mudança local | G30: Cost (GE, rework) | H30: 45554.822 | I30: 04. EMPACOTAMENTO | J30: 45770.631 | L30: APROVADORES DE IDEIAS | M30: 45770.631 | N30: Cancelado | O30: =_xlfn.XLOOKUP(TAB.IDEIAS.TOTAL[[#This Row],[Enviado por]],'BASE DMOS'!A:A,'BASE DMOS'!C:C,"Não encontrado") -> OPERAÇÃO
A31: FB0082999 | B31: Apoio fixo (pé fixo) | C31: Cancelado | D31: Soldar 5 apoio fixo com 15 cm de altura sendo dois em cada lado e um no meio Vejo que é recorrente a quebra das rodas sendo com apoio fixo não teremos mais ocorrência de quebra e com isso iremos economizar pois cada roda custa em média 700.00 cada E soldando pés teríamos pouco gastos | E31: Joelma Inone | F31: Pequena mudança local | G31: Organisation of work | H31: 45562.775 | I31: 01. LINHA 01 | J31: 45704.584 | L31: IDEIAS-VACUO | M31: 45704.584 | N31: Cancelado | O31: =_xlfn.XLOOKUP(TAB.IDEIAS.TOTAL[[#This Row],[Enviado por]],'BASE DMOS'!A:A,'BASE DMOS'!C:C,"Não encontrado") -> OPERAÇÃO
A32: FB0083266 | B32: colocar o torrador 3 para torra super claro | C32: Fechado | D32: Mesmo quando os torradores turbo 1 e 2 tiver funcionando,ligaria o torrador 3 para fazer o super claro ganharíamos na produtividade e acompanharia a máquina sempre em funcionamento não ficaria grandes período desligado não sujeitando problemas e perda de café quando precisar da máquina ela não ficará grandes período desligada , não consumiria muito o gás pq ligaria por pequeno período só para abastecer o super claro qualquer defeito seria identificado se caso problema no torrador 1 e 2 a máquina 3 estaria pronta para produzir integralmente | E32: Julho Silva | F32: Pequena mudança local | G32: Processo | H32: 45566.526 | I32: 03. TORRADOR 03 | J32: 45861.307 | K32: Igor Sousa | L32: IDEIAS-PROCESSOS | M32: 45861.307 | N32: Fechado | O32: =_xlfn.XLOOKUP(TAB.IDEIAS.TOTAL[[#This Row],[Enviado por]],'BASE DMOS'!A:A,'BASE DMOS'!C:C,"Não encontrado") -> OPERAÇÃO | P32: CANCELADO
A33: FB0083468 | B33: '+ aspirador de pó | C33: Fechado | D33: Comprar + aspirador de pó para fabrimas, para economizar tempo de cil, pois como possui apenas 1 aspirador pra 2 máquinas, sendo que uma pessoa tem q esperar desocupar o aspirador para poder usar | E33: Romero Chaves | F33: Pequena mudança local | G33: Organisation of work | H33: 45568.568 | I33: 04. LINHA 04 | J33: 45909.478 | L33: APROVADORES DE IDEIAS | M33: 45909.478 | N33: Fechado | O33: =_xlfn.XLOOKUP(TAB.IDEIAS.TOTAL[[#This Row],[Enviado por]],'BASE DMOS'!A:A,'BASE DMOS'!C:C,"Não encontrado") -> OPERAÇÃO
A34: FB0083992 | B34: Lixeira integrada na bancada para otimização de espaço | C34: Cancelado | D34: Fazer um furo com o devido acabamento no granito das bancadas da barreira sanitária para colocar as lixeiras de papel toalha embaxio da bancada e liberar espaço visto que as lixeiras estão muito proximas da catraca da barreira sanitária. Também poderia ser feito nos banheiros visto que principalmente no feminino a localização atual da lixeira pode dificultar um pouco o transito na porta do banheiro. Sugestão nas imagens em anexo As lixeiras podem ter tampas giratórias/basculantes (semelhantes como são as lixeiras inox do adm) embutidas na bancada para atender os requistos de qualidade e não ficarem abertas. | E34: Luzia Rodrigues | F34: Pequena mudança local | G34: Organisation of work | H34: 45573.612 | I34: 09.5 BANHEIROS | J34: 45797.365 | L34: IDEIAS-ADMINISTRATIVO | M34: 45797.365 | N34: Cancelado | O34: =_xlfn.XLOOKUP(TAB.IDEIAS.TOTAL[[#This Row],[Enviado por]],'BASE DMOS'!A:A,'BASE DMOS'!C:C,"Não encontrado") -> ADM/TÉCNICO/ASSISTENTE/ESTAG.
A35: FB0084063 | B35: alteração na descrição das receitas | C35: Fechado | D35: Algumas receitas não contém o número do Blend,por exemplo Damasco tradicional (Blend 40) | E35: Lucas Vaz | F35: Pequena mudança local | G35: Qualidade | H35: 45574.019 | I35: 02. TORREFAÇÃO | J35: 45846.368 | K35: Igor Sousa | L35: IDEIAS-PROCESSOS | M35: 45846.368 | N35: Fechado | O35: =_xlfn.XLOOKUP(TAB.IDEIAS.TOTAL[[#This Row],[Enviado por]],'BASE DMOS'!A:A,'BASE DMOS'!C:C,"Não encontrado") -> OPERAÇÃO
A36: FB0084739 | B36: filtrar paradas do robô | C36: Fechado | D36: IDEIA Filtrar as paradas do robô , mudando a cor das paradas ex: ( amarelo) , está dificultando muito para separar as paradas para fechar o relatório no final do turno . ------------- APROVAÇÃO Angela, excelente ideia. Demoramos para implantar, pois desde novembro estamos sem o orçamento para melhorias no MOP. Ele foi reativado agora em abril e já encaminhamos sua ideia na lista de solicitações. Para conhecimento, esse orçamento nos permite usar 3 diárias mensais de serviço especializado para alguma melhoria no MOP, então às vezes se já usamos as diárias, precisamos esperar o próximo mês para pedir algo novo. | E36: Angela Santos | F36: Pequena mudança local | G36: Cost (GE, rework) | H36: 45575.001 | I36: 04. LINHA 04 | J36: 45821.03 | K36: Giovanna Biffaratte | L36: APROVADORES DE IDEIAS | M36: 45821.03 | N36: Fechado | O36: =_xlfn.XLOOKUP(TAB.IDEIAS.TOTAL[[#This Row],[Enviado por]],'BASE DMOS'!A:A,'BASE DMOS'!C:C,"Não encontrado") -> OPERAÇÃO
A37: FB0084748 | B37: Adicionar no CIL mensal para limpeza dos utensílios de limpeza das areas | C37: Fechado | D37: Devido ao acumulo de sujeira, adicionar no CIL mensal a limpeza dos utensílios de limpeza com água ou pano. | E37: Bianca Silva | F37: Pequena mudança local | G37: Qualidade | H37: 45575.055 | I37: 01. LINHA 01 | J37: 45846.368 | K37: Bianca Silva | L37: IDEIAS-VACUO | M37: 45846.368 | N37: Fechado | O37: =_xlfn.XLOOKUP(TAB.IDEIAS.TOTAL[[#This Row],[Enviado por]],'BASE DMOS'!A:A,'BASE DMOS'!C:C,"Não encontrado") -> ADM/TÉCNICO/ASSISTENTE/ESTAG.
A38: FB0084875 | B38: Canetas sempre no chão | C38: Fechado | D38: As canetas do quadro da moagem sempre caíam, foi feito um suporte(paleativo), para acabar com este problema | E38: Camila Silva | F38: Pequena mudança local | G38: Organisation of work | H38: 45575.42 | I38: 03. MOAGEM | J38: 45595.357 | K38: Camila Silva | L38: IDEIAS-PROCESSOS | M38: 45595.357 | N38: Fechado | O38: =_xlfn.XLOOKUP(TAB.IDEIAS.TOTAL[[#This Row],[Enviado por]],'BASE DMOS'!A:A,'BASE DMOS'!C:C,"Não encontrado") -> OPERAÇÃO
A39: FB0085512 | B39: Abridor de Abas | C39: Fechado | D39: Realizar alteração no tempo de atuação do abridor de abas fazendo com que ele não entre junto com chapa frontal do enchedor para que não aja colisão na caixa fora do tempo e assim a caixa fica parada não movimento nem para traz ou para frente Ideia já discutido com Igor Eletrônico | E39: Patrick Pessoa | F39: Pequena mudança local | G39: Cost (GE, rework) | H39: 45581.419 | I39: 01. LINHA 01 | J39: 45594.544 | L39: IDEIAS-VACUO | M39: 45594.544 | N39: Fechado | O39: =_xlfn.XLOOKUP(TAB.IDEIAS.TOTAL[[#This Row],[Enviado por]],'BASE DMOS'!A:A,'BASE DMOS'!C:C,"Não encontrado") -> OPERAÇÃO
A40: FB0085628 | B40: melhoria procedimento quando arrebenta a alça do bag | C40: Em andamento | D40: quando arrebenta uma alça de bag hoje amarramos a alça com corda reaproveitada da caçamba do cavaco conforme foto. para melhorar a situação de segurança favor comprar uma cinta de 1.5m com capacidade 1500kg para está ser usada no alcamento do bag (considerando as outras 3 alças restante) Pedro Ferreira: Ideia apta para execução, mas é necessário que o orçamento seja enviado até CI, para que seja efetuada a compra. | F40: Pequena mudança local | G40: Safety - Health | H40: 45582.379 | I40: 01. CAFÉ CRU | J40: 46238.61 | K40: Flavia Silveira | L40: APROVADORES DE IDEIAS | N40: Aguardando material | O40: =_xlfn.XLOOKUP(TAB.IDEIAS.TOTAL[[#This Row],[Enviado por]],'BASE DMOS'!A:A,'BASE DMOS'!C:C,"Não encontrado") -> 0
A41: FB0085629 | B41: Moinho 1 | C41: Cancelado | D41: Eu sou analista do detector de metais e tenho que peneirar no moinho 1, e o moinho 1 a altura e muito baixa e acabando prejudicando minha postura causando dores nas costas deivido de estar muito baixo para mim,sugiro que aumentasse um pouco mais a altura. SHE: há um projeto em andamento para instalação de uma peneira vibratória no local. A peneira terá uma altura ergonômica. | E41: Emilly Silva | F41: Pequena mudança local | G41: Safety - Health | H41: 45582.397 | I41: 03. MOAGEM | J41: 45825.447 | L41: IDEIAS-PROCESSOS | M41: 45825.447 | N41: Cancelado | O41: =_xlfn.XLOOKUP(TAB.IDEIAS.TOTAL[[#This Row],[Enviado por]],'BASE DMOS'!A:A,'BASE DMOS'!C:C,"Não encontrado") -> OPERAÇÃO
A42: FB0085630 | B42: moinho 5 | C42: Em andamento | D42: Quando eu for peneira no moinho 5 a peneira é muito grande a(largura) causando a caída de café no chão, sugiro que fizeste uma peneira da largura que faz o reprocesso de café para não cair no chão,ou aumentasse mais a largura do moinho. | E42: Emilly Silva | F42: Pequena mudança local | G42: Cost (GE, rework) | H42: 45582.399 | I42: 01. MOINHO 05 | J42: 45750.423 | K42: Moises Costa | L42: IDEIAS-PROCESSOS | N42: Aguardando Aprovação de CAPEX | O42: =_xlfn.XLOOKUP(TAB.IDEIAS.TOTAL[[#This Row],[Enviado por]],'BASE DMOS'!A:A,'BASE DMOS'!C:C,"Não encontrado") -> OPERAÇÃO
A43: FB0085638 | B43: Sujeira de café na Roupa devido ao café ser peneira do | C43: Cancelado | D43: Eu Emilly Silva sou analista do detector de metais, e precisar peneira o café e onde que ocorre sujar a roupa de café, pois o café espalha muito ao peneira-lo , sugiro para não sujar muito a roupa, ja que é só eu que peneira o café de alguns turno acaba ficando muito suja a minha roupa, sugiro que eu tivesse algum jaleco para mim usar para está fazendo a devida atividade. | E43: Emilly Silva | F43: Pequena mudança local | G43: Qualidade | H43: 45582.436 | I43: 01. MOINHO 01 | J43: 45820.977 | L43: IDEIAS-PROCESSOS | M43: 45820.977 | N43: Cancelado | O43: =_xlfn.XLOOKUP(TAB.IDEIAS.TOTAL[[#This Row],[Enviado por]],'BASE DMOS'!A:A,'BASE DMOS'!C:C,"Não encontrado") -> OPERAÇÃO
A44: FB0085991 | B44: Aumento do ranger | C44: Fechado | D44: Aumentar o ranger do parâmetro tempo atraso do freio, vertical da fabrima 4 está muito curta e variando bastante quando rodado no parâmetro limite do centerlining (90) a ideia é aumentar o ranger para até 110 pois assim a vertical fica mais fixa sem variação e maior como se pode ver na imagem. | E44: Diogo Silva | F44: Pequena mudança local | G44: Cost (GE, rework) | H44: 45586.728 | I44: 04. LINHA 04 | J44: 45842.429 | L44: APROVADORES DE IDEIAS | M44: 45842.429 | N44: Fechado | O44: =_xlfn.XLOOKUP(TAB.IDEIAS.TOTAL[[#This Row],[Enviado por]],'BASE DMOS'!A:A,'BASE DMOS'!C:C,"Não encontrado") -> OPERAÇÃO
A45: FB0086147 | B45: Aumento da capacidade de armazenamento | C45: Fechado | D45: Foram cerrados paletes PBR, de forma que coubessem em baixo do rack, para ganho de espaço. Com isso ganhamos espaço e conseguimos alocar todas as etiquetas de fardo em um local mais próximo a sala do almoxarifado, facilitando seu manuseio | E45: Camila Silva | F45: Pequena mudança local | G45: Organisation of work | H45: 45587.49 | I45: 09.1 ALMOXARIFADO | J45: 45594.553 | L45: IDEIAS-CAFÉ CRÚ | M45: 45594.553 | N45: Fechado | O45: =_xlfn.XLOOKUP(TAB.IDEIAS.TOTAL[[#This Row],[Enviado por]],'BASE DMOS'!A:A,'BASE DMOS'!C:C,"Não encontrado") -> OPERAÇÃO
A46: FB0086152 | B46: EFICIÊNCIA NO PROCESSO | C46: Fechado | D46: Foi solicitado orçamento de 8 bandeijas para armário, afim de otimizar a organização. Com estas bandeijas ganhamos em: 5S ORGANIZAÇÃO TEMPO EM COMPRAS TEMPO EM CONTAGEM GANHO DE ESPAÇO ( pois conseguiremos eliminar esta prateleira da foto, deixando os uniformes apenas em armários trancados) ACURACIDADE DE ESTOQUE (facilita a contagem). | E46: Camila Silva | F46: Pequena mudança local | G46: Organisation of work | H46: 45587.502 | I46: 06. ADMINISTRATIVO | J46: 45846.447 | K46: Aline Fernandes | L46: IDEIAS-ADMINISTRATIVO | M46: 45846.447 | N46: Fechado | O46: =_xlfn.XLOOKUP(TAB.IDEIAS.TOTAL[[#This Row],[Enviado por]],'BASE DMOS'!A:A,'BASE DMOS'!C:C,"Não encontrado") -> OPERAÇÃO
A47: FB0086164 | B47: Equipamento desnecessário | C47: Cancelado | D47: Possível retirada do elevador vermelho antigo,para facilitar retirada de café em carrinhos do torrador 1 e para passagem no corredor com caçamba de descarte! Obs:Equipamento encontra-se inutilizado | E47: Lucas Vaz | F47: Pequena mudança local | G47: Processo | H47: 45587.612 | I47: 01. TORRADOR 01 | J47: 45817.609 | L47: IDEIAS-PROCESSOS | M47: 45817.609 | N47: Cancelado | O47: =_xlfn.XLOOKUP(TAB.IDEIAS.TOTAL[[#This Row],[Enviado por]],'BASE DMOS'!A:A,'BASE DMOS'!C:C,"Não encontrado") -> OPERAÇÃO
A48: FB0086390 | B48: CIL Café cru - inlcluir limpeza do elevador | C48: Resolvido | D48: no dia 23/10/24 tivemos uma parada no elevador da lançanca de CV devido a acumulo de sujeira (sacaria) e caneca. Com isso o time de manutenção realizou a limpeza e desobstrução do sistema. Este é um item de manutenção preventiva e foi feita de acordo com o tempo programado (está em dia). Tendo isto em vista, solicito a avaliação e inclusão da limpeza deste ponto no CIL. Levando em consideração que o CIL deve previnir paradas não planejadas nas máquinas que são resolvidas com limpeza. | F48: Pequena mudança local | G48: Cost (GE, rework) | H48: 45589.283 | I48: 01. CAFÉ CRU | J48: 46283.474 | K48: Flavia Silveira | L48: APROVADORES DE IDEIAS | N48: Resolvido | O48: =_xlfn.XLOOKUP(TAB.IDEIAS.TOTAL[[#This Row],[Enviado por]],'BASE DMOS'!A:A,'BASE DMOS'!C:C,"Não encontrado") -> 0
A49: FB0086521 | B49: portao da entrada de caminhões | C49: Cancelado | D49: Fazer a troca por um portão automático porque acaba exigindo muito esforço físico dos terceiros da portaria, como travamento do portão em dias de chuva emperra entre outros. | E49: Sara Lobato | F49: Pequena mudança local | G49: Safety - Health | H49: 45590.329 | I49: 09.14 PORTARIA | J49: 45817.613 | L49: IDEIAS-ADMINISTRATIVO | M49: 45817.613 | N49: Cancelado | O49: =_xlfn.XLOOKUP(TAB.IDEIAS.TOTAL[[#This Row],[Enviado por]],'BASE DMOS'!A:A,'BASE DMOS'!C:C,"Não encontrado") -> OPERAÇÃO
A50: FB0086839 | B50: Ligação independente para codificadora de caixas | C50: Em andamento | D50: Colocar uma ligação independente para codificadora de caixas da ligação da encaixotadora. Atualmente se desligar a geral da encaixotadora já desliga automaticamente a codificadora de caixas, porém ela precisa de um procedimento de desligamento mais demorado conforme treinamento que foi ministrado pelo técnico no ano passado após as grandes ocorrências que tivemos na codificadora. Manutenção: Precisamos fazer orçamento com Eletromarzinho para a instalação de infra para passagem de cabos. | E50: Michelle Faria | F50: Pequena mudança local | G50: Processo | H50: 45594.157 | I50: 01. LINHA 01 | J50: 45859.447 | K50: Igor Sousa | L50: IDEIAS-VACUO | N50: Cancelado | O50: =_xlfn.XLOOKUP(TAB.IDEIAS.TOTAL[[#This Row],[Enviado por]],'BASE DMOS'!A:A,'BASE DMOS'!C:C,"Não encontrado") -> ADM/TÉCNICO/ASSISTENTE/ESTAG. | P50: CANCELADO
A51: FB0087054 | B51: Raumak 2 Eliminar o motor desbobinador | C51: Resolvido | D51: IDEIA Eliminar o motor desbobinador da Raumak 2, para evitar a queda do motor e evitar paradas da Raumak devido a causa que é feita o motor desbobinador da Raumak 2, e sugiro que seja feita a eliminação do motor desbobinador e colocasse a Raumak 2 e a bailarina também, colocasse a Raumak 2 que nem as Raumak 3,4 e 5. Pois mudando a Raumak 2 que nem ás Raumak 3,4 e 5, Ficaria com mais fácil acesso e evitaria a queda do motor e teria mais fácil acesso com a bobina na hora da troca pois o modo que é feito a Bailarina é o motor fica difícil com difícil acesso e a bobina e o motor não cairia,e não causaria nenhum acidente de lesão leve. Colocando a Raumak 2 que nem a Raumak 3,4 e 5 e que nem as bailarinas ficariam com mais fácil acesso e ficariam melhor. --------- APROVAÇÃO Visto durante o plantão de ideias com a Emilly que a ideia está com o Arthur para viabilidade técnica. Prover atualização. Solicitado a Emilly também a adição de fotos. | E51: Emilly Silva | F51: Pequena mudança local | G51: Safety - Health | H51: 45595.421 | I51: 02. LINHA 02 | J51: 45989.467 | L51: APROVADORES DE IDEIAS | N51: Resolvido | O51: =_xlfn.XLOOKUP(TAB.IDEIAS.TOTAL[[#This Row],[Enviado por]],'BASE DMOS'!A:A,'BASE DMOS'!C:C,"Não encontrado") -> OPERAÇÃO
A52: FB0087078 | B52: Projeto faixas para estacionamento | C52: Fechado | D52: Projeto consiste na pintura de faixas para organização das carretas inbound e outbound no espaço lateral no pátio externo da logística | E52: Diego T Oliveira | F52: Pequena mudança local | G52: Organisation of work | H52: 45595.638 | I52: 08. LOGISTICA | J52: 45835.453 | K52: Fabio A Oliveira | L52: IDEIAS-LOGÍSTICA | M52: 45835.453 | N52: Fechado | O52: =_xlfn.XLOOKUP(TAB.IDEIAS.TOTAL[[#This Row],[Enviado por]],'BASE DMOS'!A:A,'BASE DMOS'!C:C,"Não encontrado") -> OPERAÇÃO
A53: FB0087113 | B53: tomada para conectar o aspirador entre a Raumak e robô linha 2-3 | C53: Resolvido | D53: Entre a Raumak e robô da linha 2-3 não tem tomada que adapta o aspirador, pois a entrega da tomada dele é grossa | E53: Angela Santos | F53: Pequena mudança local | G53: Processo | H53: 45596.07 | I53: 02. LINHA 02 | J53: 46226.499 | K53: Anderson Santana | L53: APROVADORES DE IDEIAS | N53: Resolvido | O53: =_xlfn.XLOOKUP(TAB.IDEIAS.TOTAL[[#This Row],[Enviado por]],'BASE DMOS'!A:A,'BASE DMOS'!C:C,"Não encontrado") -> OPERAÇÃO
A54: FB0087245 | B54: colocar as limpeza t3 cil | C54: Resolvido | D54: Não tem no cil | E54: Julho Silva | F54: Pequena mudança local | G54: Qualidade | H54: 45596.582 | I54: 02. TORREFAÇÃO | J54: 46282.433 | K54: Flavia Silveira | L54: APROVADORES DE IDEIAS | N54: Cancelado | O54: =_xlfn.XLOOKUP(TAB.IDEIAS.TOTAL[[#This Row],[Enviado por]],'BASE DMOS'!A:A,'BASE DMOS'!C:C,"Não encontrado") -> OPERAÇÃO | P54: CANCELADO
A55: FB0087246 | B55: rosca de película 1 e 2 por no cil | C55: Fechado | D55: Precisar fazer raspagem as crosta que forma | E55: Julho Silva | F55: Pequena mudança local | G55: Product | H55: 45596.583 | I55: 02. TORREFAÇÃO | J55: 45966.371 | K55: Bianca Silva | L55: IDEIAS-PROCESSOS | M55: 45966.371 | N55: Fechado | O55: =_xlfn.XLOOKUP(TAB.IDEIAS.TOTAL[[#This Row],[Enviado por]],'BASE DMOS'!A:A,'BASE DMOS'!C:C,"Não encontrado") -> OPERAÇÃO
A56: FB0087260 | B56: aspirador pneumático pra facilitar a limpeza parte superior dos silos | C56: Fechado | D56: Aspirador de pó, facilitando os trabalhos em altura onde temos que fazer limpeza de fim de mês ou qualquer outra atividade em altura E a não ter que ficar jogando toda aquela quantidade de pó e sujeira no chão tendo que fazer dois trabalhos num só Esse aspirador poderíamos está vendo uma maneira fácil de tá usando ele com o cinto de segurança E seria interessante também aderirmos a compra de um pra cada área assim como a cor da area Tendo o produto pronto não teriamos mais a limpeza com ar comprimido facilitando e muito nosso trabalho e a limpeza | E56: Alex Teixeira | F56: Pequena mudança local | G56: Organisation of work | H56: 45596.795 | I56: 03. MOAGEM | J56: 46029.573 | K56: Ricardo Nishida | L56: IDEIAS-PROCESSOS | M56: 46029.573 | N56: Fechado | O56: =_xlfn.XLOOKUP(TAB.IDEIAS.TOTAL[[#This Row],[Enviado por]],'BASE DMOS'!A:A,'BASE DMOS'!C:C,"Não encontrado") -> OPERAÇÃO
A57: FB0087261 | B57: Melhoria de ergonomia para limpeza das Câmaras de torra | C57: Fechado | D57: Realizar compra de um desincrustador pneumático para facilitar a limpeza das câmaras de torra, gerando mais facilidade e retirando o uso de espátula e marreta. Isso irá reduzir o tempo de limpeza, reduzindo também a exposição do associado ao risco de NR33, além dos benefícios a ergonomia da atividade. | E57: Edvaldo Silva | F57: Pequena mudança local | G57: Safety - Health | H57: 45596.89 | I57: 02. TORREFAÇÃO | J57: 45819.615 | K57: Ricardo Nishida | L57: IDEIAS-PROCESSOS | M57: 45819.615 | N57: Fechado | O57: =_xlfn.XLOOKUP(TAB.IDEIAS.TOTAL[[#This Row],[Enviado por]],'BASE DMOS'!A:A,'BASE DMOS'!C:C,"Não encontrado") -> OPERAÇÃO
A58: FB0087369 | B58: Melhoria Torrador 3 | C58: Resolvido | D58: Criação de uma porta na lateral no torrador 3.. para facilitar a condição de limpeza de películas na parte inferior do mesmo, local onde é espaço confinado, de difícil acesso, péssima ergonomia e acumula muita sujeira. Esse local faz parte da rotina de limpeza diária, sendo necessário limpar todo início de produção ( geralmente aos domingos ). Com essa sugestão seria possível realizar a limpeza de uma forma mais segura, ágil , e sem a necessidade de um operador adentrar ao espaço confinado eliminando a abertura de PT, separar um associado para vigia, e socorrista, sendo possível priorizar outras atividades. | E58: Vinicius De Oliveira | F58: Pequena mudança local | G58: Safety - Health | H58: 45597.976 | I58: 02. TORREFAÇÃO | J58: 46106.479 | K58: Izabela Pugliesi | L58: IDEIAS-PROCESSOS | N58: Resolvido | O58: =_xlfn.XLOOKUP(TAB.IDEIAS.TOTAL[[#This Row],[Enviado por]],'BASE DMOS'!A:A,'BASE DMOS'!C:C,"Não encontrado") -> OPERAÇÃO | P58: CANCELADO
A59: FB0087415 | B59: melhoria na fixação das pinças superior e inferior da formação do fundo PKD | C59: Em andamento | D59: Melhoria na fixação das pinças superior e inferior da formação do fundo PKD Deve ser realizado a confecção de duas pinças novas com o furo de fixação com a medida exata do parafuso para que não haja folga nem ajuste neste ponto | E59: Arthur Silva | F59: Pequena mudança local | G59: Qualidade | H59: 45599.281 | I59: 01. LINHA 01 | J59: 45602.571 | K59: Andre Mendes Costa | L59: IDEIAS-VACUO | N59: Aguardando Execução | O59: =_xlfn.XLOOKUP(TAB.IDEIAS.TOTAL[[#This Row],[Enviado por]],'BASE DMOS'!A:A,'BASE DMOS'!C:C,"Não encontrado") -> ADM/TÉCNICO/ASSISTENTE/ESTAG.
A60: FB0087474 | B60: transporte café torrado do torrador3 | C60: Fechado | D60: Implementar tela do transporte de café torrado na tela principal do torrador 3 Semelhante à dos turbo 1 e 2 | E60: Lucas Vaz | F60: Pequena mudança local | G60: Organisation of work | H60: 45600.35 | I60: 02. TORREFAÇÃO | J60: 45846.368 | K60: Igor Sousa | L60: IDEIAS-PROCESSOS | M60: 45846.368 | N60: Fechado | O60: =_xlfn.XLOOKUP(TAB.IDEIAS.TOTAL[[#This Row],[Enviado por]],'BASE DMOS'!A:A,'BASE DMOS'!C:C,"Não encontrado") -> OPERAÇÃO
A61: FB0087661 | B61: ALTERAÇÃO DO MODELO DE CILINDRO DO BRAÇO DOBRADOR DE ABAS DA ENCAIXOTADORA | C61: Resolvido | D61: DESENVOLVER UM MODELO DE CILINDRO PNEUMÁTICO QUE TENHA MAIS RESISTENCIA A IMPACTOS POR TORÇÃO E POSSUA SISTEMA DE AMORTECIMENTO DE FIM DE CURSO - AÇÃO DA BDA RCA0195536 , ONDE HOUVE A QUEBRA DO EIXO DESSE CILINDRO | E61: Henrique Cardoso | F61: Pequena mudança local | G61: Cost (GE, rework) | H61: 45601.826 | I61: 01. LINHA 01 | J61: 46265.428 | K61: Henrique Cardoso | L61: APROVADORES DE IDEIAS | N61: Resolvido | O61: =_xlfn.XLOOKUP(TAB.IDEIAS.TOTAL[[#This Row],[Enviado por]],'BASE DMOS'!A:A,'BASE DMOS'!C:C,"Não encontrado") -> ADM/TÉCNICO/ASSISTENTE/ESTAG. | P61: CANCELADO
A62: FB0087799 | B62: Melhoria na visualização dos cames da roda de mandril (formação do fundo) | C62: Fechado | D62: Substituir a tampa de proteção dos cames para uma tampa em acrílico transparente para facilitar a visualização do alinhamento dos cames | E62: Relton Moraes | F62: Pequena mudança local | G62: Qualidade | H62: 45602.578 | I62: 01. JDE CAFES DO BRASIL UNIDADE PIUMHI | J62: 45842.426 | K62: Andre Mendes Costa | L62: IDEIAS-MELHORIA CONTÍNUA | M62: 45842.426 | N62: Fechado | O62: =_xlfn.XLOOKUP(TAB.IDEIAS.TOTAL[[#This Row],[Enviado por]],'BASE DMOS'!A:A,'BASE DMOS'!C:C,"Não encontrado") -> ADM/TÉCNICO/ASSISTENTE/ESTAG.
A63: FB0087827 | B63: INSTALAR JANELA DE INSPEÇÃO PARA ACESSO AOS REGISTROS DE CALOR DE CADA UMA DAS CÂMARAS DOS TORRADORES | C63: Cancelado | D63: AVALIAR POSSIBILIDADE DE INSTALAR UMA JANELA DE INSPEÇÃO PARA ACESSO AOS REGISTROS DE CALOR DAS CAMARAS DE TORRA (DUMPERS DE AR QUENTE) NA PARTE EXTERNA DA FORNALHA, (PRINCIPALMENTE PARA O DUMPER DA CAMARA 2 QUE FICA EM UM DUTO EM "L"). ISSO ELIMINARIA A NECESSIDADE DE ESPAÇO CONFINADO PARA REALIZAR A MANUTENÇÃO PREVENTIVA, PROPORCIONANDO REDUÇÃO DE TEMPO E ELIMINAÇÃO DE ATIVIDADE DE RISCO OBS: AÇÃO SAIU DO FMEA00002 DO REGISTRO DE CALOR DO TORRADOR 1 | E63: Henrique Cardoso | F63: Pequena mudança local | G63: Safety - Health | H63: 45602.832 | I63: 01. TORRADORES | J63: 45797.472 | L63: IDEIAS-PROCESSOS | M63: 45797.472 | N63: Cancelado | O63: =_xlfn.XLOOKUP(TAB.IDEIAS.TOTAL[[#This Row],[Enviado por]],'BASE DMOS'!A:A,'BASE DMOS'!C:C,"Não encontrado") -> ADM/TÉCNICO/ASSISTENTE/ESTAG. | P63: CANCELADO
A64: FB0087861 | B64: Cobertura para empilhadeira | C64: Em andamento | D64: A área demarcada em vermelho destaca áreas críticas do painel onde costuma infiltrar água toda vez que necessita jogar película na caçamba de resíduos do lado de fora. Quando molha o painel apresentam informações no mesmo de ordem elétrica,impedindo o funcionamento do equipamento. Creio que este equipamento não foi feito para se andar na chuva,pois uma cobertura sobre o equipamento já resolveria esta situação. | E64: Jose Junior | F64: Pequena mudança local | G64: Organisation of work | H64: 45603.143 | I64: 01. CAFÉ CRU | J64: 46238.613 | K64: Flavia Silveira | L64: APROVADORES DE IDEIAS | N64: Aguardando Validação | O64: =_xlfn.XLOOKUP(TAB.IDEIAS.TOTAL[[#This Row],[Enviado por]],'BASE DMOS'!A:A,'BASE DMOS'!C:C,"Não encontrado") -> OPERAÇÃO
A65: FB0087866 | B65: RODÍZIO SOB OS TAMBORES DOS CICLONES | C65: Fechado | D65: Estes ciclones quando retirados do local para a limpeza são pesados,e para facilitar sua locomoção até o descarte seria ideal rodízios neles. Pois removê-los todos os dias é incômodo pois se faz movimentos semi-flexionados,causando dor na região lombar da coluna. | E65: Jose Junior | F65: Pequena mudança local | G65: Safety - Health | H65: 45603.151 | I65: 01. CAFÉ CRU | J65: 45846.365 | K65: Caique Ventura | L65: IDEIAS-CAFÉ CRÚ | M65: 45846.365 | N65: Fechado | O65: =_xlfn.XLOOKUP(TAB.IDEIAS.TOTAL[[#This Row],[Enviado por]],'BASE DMOS'!A:A,'BASE DMOS'!C:C,"Não encontrado") -> OPERAÇÃO
A66: FB0088026 | B66: MOP em constante EVOLUÇÃO | C66: Fechado | D66: IDEIA Futuramente ter a opção de fazer nossos apontamentos com fotos .. podendo assim de uma maneira mais clara e objetiva para o entendimento de todos . Muitas vezes nós não sabemos com palavra explicar a REAL causa da parada. Facilitando assim o entendimento de todos -------------------------------- FEEDBACKS Giovanna - 18/12: Lais, o MOP não vamos conseguir trazer essa funcionalidade pos restrição de desenvolvimento e porque temos a questão da foto no DMOS. Porém sua solicitação está muito em linha com algo que estamos pensando: estamos trabalhando para a ordem branca virar uma etiqueta do DMOS. Com isso, quando houver problema na máquina com atendimento técnico ou próprio operacional, o operador abrirá a etiqueta no DMOS (onde pode colocar foto) e colocará o número da etiqueta no apontamento do MOP, assim podemos ver a foto do problema, conforme sua solicitação! Além disso, com base na sua ideia, vou programar com o time de CI, para pegarmos os códigos da árvore de perdas e de fato colocarmos fotos dos pontos para que seja um norte. (Relton, tocar isso, por favor) Com esses dois pontos que não são exatamente a sua ideia mas entregam o mesmo valor eu vou aprovar a ideia, mas considerando as execuções acima, tudo bem? Quer adicionar algo mais? -------------------------------- | E66: Lais Silveira | F66: Pequena mudança local | G66: Cost (GE, rework) | H66: 45604.111 | I66: 01. JDE CAFES DO BRASIL UNIDADE PIUMHI | J66: 45846.367 | K66: Relton Moraes | L66: IDEIAS-MELHORIA CONTÍNUA | M66: 45846.367 | N66: Fechado | O66: =_xlfn.XLOOKUP(TAB.IDEIAS.TOTAL[[#This Row],[Enviado por]],'BASE DMOS'!A:A,'BASE DMOS'!C:C,"Não encontrado") -> OPERAÇÃO
A67: FB0088085 | B67: Suporte para redução de carga das calhas | C67: Cancelado | D67: Suporte para redução de carga das calhas para não parar a rosca e dar alarme | E67: Leonardo Junior | F67: Pequena mudança local | G67: Organisation of work | H67: 45604.411 | I67: 01. JDE CAFES DO BRASIL UNIDADE PIUMHI | J67: 45604.415 | L67: IDEIAS-MELHORIA CONTÍNUA | M67: 45604.415 | N67: Cancelado | O67: =_xlfn.XLOOKUP(TAB.IDEIAS.TOTAL[[#This Row],[Enviado por]],'BASE DMOS'!A:A,'BASE DMOS'!C:C,"Não encontrado") -> OPERAÇÃO
A68: FB0088140 | B68: suporte para redução de vazão das calhas | C68: Fechado | D68: suporte para redução de vazão das calhas, de recebimento café cru, para não parar a rosca e ocasionar alarme | E68: Nilton F Costa | F68: Pequena mudança local | G68: Cost (GE, rework) | H68: 45605.323 | I68: 01. CAFÉ CRU | J68: 45616.653 | L68: IDEIAS-CAFÉ CRÚ | M68: 45616.653 | N68: Fechado | O68: =_xlfn.XLOOKUP(TAB.IDEIAS.TOTAL[[#This Row],[Enviado por]],'BASE DMOS'!A:A,'BASE DMOS'!C:C,"Não encontrado") -> OPERAÇÃO
A69: FB0088323 | B69: Melhoria de Ponto de Aromatização da Película | C69: Em andamento | D69: Hoje atualmente os coletores de cinza são transportados para rosca de plana da película. Na rosca plana de película existe 2 pontos de aromatização, o segundo ponto conforme a foto ilustrada é bem ao lado onde a rosca inclinada de cinza recebe toda cinza coletada trazendo para a plana de película. Atualmente temos vários registros de obstrução no micro final da rosca inclinada de cinza que cai junto com a plana de película, essa obstrução ela ocorre devido que o ponto de aromatização de película é ao lado onde cai toda cinza, como a rosca de cinza trabalha em temperatura alta devido a cinza e como a aromatização é bem ao lado conforme a foto ocorre vapor e suando no berço da rosca e como a cinza vai empreguinando vai ocorrendo obstrução da cinza e encrostando até acionando do Micro do final da rosca de cinza. A ideia é mudar o ponto de aromatização da rosca plana de película para segunda foto ilustrada para que não ocorra essas diversas obstrução de cinza e assim reduzimos nossos impactos de MTBB e MTBF. Pedro Ferreira: Ideia pode ser realizada através da Manutenção, entretanto, caso não for possível, Rubens irá ficar responsável em solicitar orçamento. | E69: Edvaldo Silva | F69: Pequena mudança local | G69: Cost (GE, rework) | H69: 45607.789 | I69: 02. TORREFAÇÃO | J69: 45925.642 | K69: Rubens Teixeira | L69: IDEIAS-PROCESSOS | N69: Aguardando Orçamento | O69: =_xlfn.XLOOKUP(TAB.IDEIAS.TOTAL[[#This Row],[Enviado por]],'BASE DMOS'!A:A,'BASE DMOS'!C:C,"Não encontrado") -> OPERAÇÃO
A70: FB0088336 | B70: local de difícil acesso para limpeza | C70: Cancelado | D70: Acrílicos e tubo do arremessador de difícil acesso para limpeza na parte superior da Raumak 2 A ideia seria adicionar uma porta com NR para ter um acesso melhor ao arremessador e aos acrílicos do fundo. SHE: ideia aprovada. Proximos passos: 1-Orçar a mudança com o fornecedor (ENG); 2-Realizar a apreciação de risco NR-12 (+/- R$ 8.000); 3-Laudo de Proteção de Máquinas (NR-12); Pedro Ferreira: Ideia será CANCELADA devido alto custo. | F70: Pequena mudança local | G70: Organisation of work | H70: 45607.917 | I70: 02. LINHA 02 | J70: 45903.629 | L70: APROVADORES DE IDEIAS | M70: 45903.629 | N70: Cancelado | O70: =_xlfn.XLOOKUP(TAB.IDEIAS.TOTAL[[#This Row],[Enviado por]],'BASE DMOS'!A:A,'BASE DMOS'!C:C,"Não encontrado") -> 0
A71: FB0088344 | B71: Espaço estreito | C71: Resolvido | D71: Coletor de variação de peso muito grande, dificultando bastante o ir e vir na linha. A posição dele é bem de frente a pilastra o que atrapalha ainda mais. Solicito diminuir o tamanho dele pelo tamanho padrão das outras fabrimas , pois a linha 03 já é bem pequena o que facilita a colisão em diversas vezes com nosso corpo gerando algumas lesões | E71: Lais Silveira | F71: Pequena mudança local | G71: Safety - Health | H71: 45608.006 | I71: 03. LINHA 03 | J71: 45960.602 | K71: Michelle Faria | L71: APROVADORES DE IDEIAS | N71: Resolvido | O71: =_xlfn.XLOOKUP(TAB.IDEIAS.TOTAL[[#This Row],[Enviado por]],'BASE DMOS'!A:A,'BASE DMOS'!C:C,"Não encontrado") -> OPERAÇÃO
A72: FB0088501 | B72: Melhoria no óculos de segurança | C72: Resolvido | D72: Devido uso obrigatório de óculos de segurança para quaisquer atividades e como EPI seria interessante adaptar todos os óculos com uma borracha de silicone ou outra do tipo para que não incomodar ao colocar sobre o nariz usaremos as borracha no desenho do encaixa das guia conforme a foto ilustrada. Essa nova adaptação seria para amenizar o incômodo de aperto das guia do óculos, já que os atuais não existi. SHE: Reprovado. | E72: Edvaldo Silva | F72: Pequena mudança local | G72: Safety - Health | H72: 45608.788 | I72: 09.19 SALA DE PRODUTOS QUÍMICOS | J72: 46099.4 | L72: IDEIAS-SHE | N72: Resolvido | O72: =_xlfn.XLOOKUP(TAB.IDEIAS.TOTAL[[#This Row],[Enviado por]],'BASE DMOS'!A:A,'BASE DMOS'!C:C,"Não encontrado") -> OPERAÇÃO
A73: FB0088522 | B73: Placa Visual | C73: Fechado | D73: Colocar uma placa visual na linha de produção, procedimento de lavagem dos filtros para estabelecer a padronização da limpeza dos filtros. | E73: Vitor Xavier | F73: Pequena mudança local | G73: Cost (GE, rework) | H73: 45608.968 | I73: 01. LINHA 01 | J73: 45922.626 | K73: Pedro Ferreira | L73: IDEIAS-VACUO | M73: 45922.626 | N73: Fechado | O73: =_xlfn.XLOOKUP(TAB.IDEIAS.TOTAL[[#This Row],[Enviado por]],'BASE DMOS'!A:A,'BASE DMOS'!C:C,"Não encontrado") -> OPERAÇÃO
A74: FB0088523 | B74: café no início do turno | C74: Fechado | D74: Seria muito bom chegar no turno e ter um café fresco , tem vezes que o café so fica pronto umas 23:00, o segundo turno poderia deixar uma garrafa pronta | E74: Angela Santos | F74: Pequena mudança local | G74: Organisation of work | H74: 45608.98 | I74: 06. ADMINISTRATIVO | J74: 45628.577 | K74: Ana Pereira | L74: IDEIAS-ADMINISTRATIVO | M74: 45628.577 | N74: Fechado | O74: =_xlfn.XLOOKUP(TAB.IDEIAS.TOTAL[[#This Row],[Enviado por]],'BASE DMOS'!A:A,'BASE DMOS'!C:C,"Não encontrado") -> OPERAÇÃO
A75: FB0088563 | B75: Carrinho PKD | C75: Resolvido | D75: Fazer a compra de ou carrinho para agilizar a troca de produto, devido as bobinas serem grandes. Foi necessário utilizar o carrinho das fabrimas não adequado. | E75: Vitor Xavier | F75: Pequena mudança local | G75: Product | H75: 45609.197 | I75: 01. LINHA 01 | J75: 45752.508 | K75: Tiago Carvalho | L75: IDEIAS-VACUO | N75: Resolvido | O75: =_xlfn.XLOOKUP(TAB.IDEIAS.TOTAL[[#This Row],[Enviado por]],'BASE DMOS'!A:A,'BASE DMOS'!C:C,"Não encontrado") -> OPERAÇÃO
A76: FB0089309 | B76: Padronização dos batentes nas esteiras das fabrimas 2 e 3 e máquinas 4 e 5 | C76: Fechado | D76: Sugestão partiu da necessidade de padronização dos batentes nas esteiras das fab 2 e 3 e maq 4 e 5 de acordo com a da esteira da PKD , o que traria a devida segurança e facilidade para trabalho. O padrão seria igual o atual instalado na PKD conforme foto em anexo. | E76: Fabio A Oliveira | F76: Pequena mudança local | G76: Processo | H76: 45615.597 | I76: 08. LOGISTICA | J76: 45835.453 | K76: Fabio A Oliveira | L76: IDEIAS-LOGÍSTICA | M76: 45835.453 | N76: Fechado | O76: =_xlfn.XLOOKUP(TAB.IDEIAS.TOTAL[[#This Row],[Enviado por]],'BASE DMOS'!A:A,'BASE DMOS'!C:C,"Não encontrado") -> ADM/TÉCNICO/ASSISTENTE/ESTAG.
A77: FB0089384 | B77: certificado | C77: Fechado | D77: Solicito que analisem a possibilidade de entregar certificado para os associados que concluírem o treinamento da apostila ( programa de capacitação) que deu início no mês de outubro. | E77: Iranildo Costa | F77: Pequena mudança local | G77: Organisation of work | H77: 45616.361 | I77: 04. EMPACOTAMENTO | J77: 45959.624 | K77: Luzia Rodrigues | L77: APROVADORES DE IDEIAS | M77: 45959.624 | N77: Fechado | O77: =_xlfn.XLOOKUP(TAB.IDEIAS.TOTAL[[#This Row],[Enviado por]],'BASE DMOS'!A:A,'BASE DMOS'!C:C,"Não encontrado") -> OPERAÇÃO
A78: FB0089726 | B78: Fita de isolamento mais eficiente | C78: Em andamento | D78: A PROPOSTA DA IDEIA DE MELHORIA É SUBSTITUIR O USO DE FITA DE ISOLAMENTO DESCARTAVEL POR FITA RETRÁTIL, ESSA FITA RETRÁTIL SERIA INSTALADA POR MÁQUINA, DE FORMA QUE FAVOREÇA MUITAS CONFIGURAÇÕES DE ISOLAMENTO UTILIZANDO UM UNICO ISOLAMENTO. Com essa ideia mapiei os seguintes ganhos: - Melhorar a eficiência do isolamento: Proporcionar um posicionamento otimizado do suporte para fita de isolamento, garantindo sua utilização prática e eficaz. - Aumentar a agilidade no processo de isolamento: Reduzir o tempo necessário para localizar e utilizar a fita, através de suportes individuais dedicados a cada máquina. - Garantir a execução consistente do isolamento: Evitar falhas no processo devido à indisponibilidade ou dificuldade em encontrar o material necessário. - Promover a sustentabilidade: Minimizar o consumo excessivo de fita plástica de isolamento, incentivando o uso racional do material. Demais associados envolvido na ideia: Alexandre Assis e Guilherme Oliveira Giovanna - 18/12: Tiago, por favor, poderia avaliar essa alteração junto ao Guilherme? Creio que verba para tal pode ser para um teste piloto do Prog de ideias e depois da área de SHE, caso possuam. | E78: Talita Campos | F78: Pequena mudança local | G78: Safety - Health | H78: 45619.719 | I78: 06. ADMINISTRATIVO | J78: 46206.452 | K78: Tiago Carvalho | L78: APROVADORES DE IDEIAS | N78: Aguardando Orçamento | O78: =_xlfn.XLOOKUP(TAB.IDEIAS.TOTAL[[#This Row],[Enviado por]],'BASE DMOS'!A:A,'BASE DMOS'!C:C,"Não encontrado") -> ADM/TÉCNICO/ASSISTENTE/ESTAG.
A79: FB0090012 | B79: Criar procedimento para abastecimento da maquina com café | C79: Em andamento | D79: Criar uma IT com passo a passo ensinando a abastecer a maquina com café empacotamento | E79: Relton Moraes | F79: Pequena mudança local | G79: Processo | H79: 45622.498 | I79: 04. EMPACOTAMENTO | J79: 45644.645 | K79: Relton Moraes | L79: APROVADORES DE IDEIAS | N79: Aguardando Execução | O79: =_xlfn.XLOOKUP(TAB.IDEIAS.TOTAL[[#This Row],[Enviado por]],'BASE DMOS'!A:A,'BASE DMOS'!C:C,"Não encontrado") -> ADM/TÉCNICO/ASSISTENTE/ESTAG.
A80: FB0090264 | B80: protecao de parada do pallet linha 04 | C80: Fechado | D80: Fazer igual o da PKD | E80: Daniel Madureira | F80: Pequena mudança local | G80: Product | H80: 45624.168 | I80: 04. LINHA 04 | J80: 45846.367 | K80: Fabio A Oliveira | L80: APROVADORES DE IDEIAS | M80: 45846.367 | N80: Fechado | O80: =_xlfn.XLOOKUP(TAB.IDEIAS.TOTAL[[#This Row],[Enviado por]],'BASE DMOS'!A:A,'BASE DMOS'!C:C,"Não encontrado") -> OPERAÇÃO
A81: FB0090522 | B81: Criar procedimento para troca de teflon do tubo formador de pacotes | C81: Fechado | D81: Realizar a criação de um procedimento para troca de teflon do tubo formador de pacotes | E81: Relton Moraes | F81: Pequena mudança local | G81: Processo | H81: 45625.712 | I81: 04. EMPACOTAMENTO | J81: 45919.558 | K81: Relton Moraes | L81: APROVADORES DE IDEIAS | M81: 45919.558 | N81: Fechado | O81: =_xlfn.XLOOKUP(TAB.IDEIAS.TOTAL[[#This Row],[Enviado por]],'BASE DMOS'!A:A,'BASE DMOS'!C:C,"Não encontrado") -> ADM/TÉCNICO/ASSISTENTE/ESTAG.
A82: FB0090523 | B82: Criar procedimento para corrigir a variação de peso das fabrimas | C82: Em andamento | D82: Criar procedimento para corrigir a variação de peso das fabrimas | E82: Relton Moraes | F82: Pequena mudança local | G82: Processo | H82: 45625.714 | I82: 04. EMPACOTAMENTO | J82: 45919.569 | K82: Relton Moraes | L82: APROVADORES DE IDEIAS | N82: Aguardando Execução | O82: =_xlfn.XLOOKUP(TAB.IDEIAS.TOTAL[[#This Row],[Enviado por]],'BASE DMOS'!A:A,'BASE DMOS'!C:C,"Não encontrado") -> ADM/TÉCNICO/ASSISTENTE/ESTAG.
A83: FB0090526 | B83: criar procedimento de troca do teflon da vertical da fabrima | C83: Fechado | D83: criar procedimento de troca do teflon da vertical da fabrima | E83: Relton Moraes | F83: Pequena mudança local | G83: Processo | H83: 45625.732 | I83: 04. EMPACOTAMENTO | J83: 45919.57 | K83: Relton Moraes | L83: APROVADORES DE IDEIAS | M83: 45919.57 | N83: Fechado | O83: =_xlfn.XLOOKUP(TAB.IDEIAS.TOTAL[[#This Row],[Enviado por]],'BASE DMOS'!A:A,'BASE DMOS'!C:C,"Não encontrado") -> ADM/TÉCNICO/ASSISTENTE/ESTAG.
A84: FB0090527 | B84: Porta absorvente | C84: Cancelado | D84: Porta absorvente, banheiro feminino pra quando precisar | E84: Karina Silva | F84: Pequena mudança local | G84: Safety - Health | H84: 45625.733 | I84: 09.5 BANHEIROS | J84: 45908.479 | L84: IDEIAS-ADMINISTRATIVO | M84: 45908.479 | N84: Cancelado | O84: =_xlfn.XLOOKUP(TAB.IDEIAS.TOTAL[[#This Row],[Enviado por]],'BASE DMOS'!A:A,'BASE DMOS'!C:C,"Não encontrado") -> OPERAÇÃO
A85: FB0091085 | B85: CIL, no robô diário | C85: Fechado | D85: Colocar o CIL , no robô diário , pois não tem para a limpeza do chão | E85: Angela Santos | F85: Pequena mudança local | G85: Qualidade | H85: 45630.98 | I85: 05. LINHA 05 | J85: 45873.251 | K85: Bianca Silva | L85: APROVADORES DE IDEIAS | M85: 45873.251 | N85: Fechado | O85: =_xlfn.XLOOKUP(TAB.IDEIAS.TOTAL[[#This Row],[Enviado por]],'BASE DMOS'!A:A,'BASE DMOS'!C:C,"Não encontrado") -> OPERAÇÃO
A86: FB0091212 | B86: LOTOTO descarga café cru | C86: Resolvido | D86: ao realizar a auditoria de LOTOTO durante a descarga de café e observei algumas oportunidades. Atualmente não é aplicado corretamente, o claviculário fica em um ponto pouco estratégico e não traz a identidade visual do novo LOTOTO e sabemos que isso tem ligação direta com cultura. Então minha sugestão é a elaboração de um "quadro de LOTOTO" para esse ponto, além de incluirmos uma cadeado especifico para o uso do motorista, pois temos relatos de alguns deles serem relutante de deixar a chave do caminhão na mão de nossos operadores. Acredito que a implementação dessa ideia contribuirá para a eficácia do procedimento Demais associados envolvido na ideia: Ricardo Barbosa e Valdecir SHE: o procedimento de LOTOTO se aplica a bloqueio de energia em máquinas e equipamentos. O processo de guarda e bloqueio da chave dos motoristas de carreta não se enquadra em LOTOTO. A pratica da guarda das chaves já é usada na logistica. Gentileza visistar a logistica e aplicar no café crú a pratica usada por eles. Ideia reprovada por SHE. | E86: Talita Campos | F86: Pequena mudança local | G86: Safety - Health | H86: 45631.865 | I86: 01. CAFÉ CRU | J86: 46148.481 | K86: Guilherme Oliveira | L86: IDEIAS-CAFÉ CRÚ | N86: Resolvido | O86: =_xlfn.XLOOKUP(TAB.IDEIAS.TOTAL[[#This Row],[Enviado por]],'BASE DMOS'!A:A,'BASE DMOS'!C:C,"Não encontrado") -> ADM/TÉCNICO/ASSISTENTE/ESTAG. | P86: CANCELADO
A87: FB0091219 | B87: medicação para o terceiro turno | C87: Resolvido | D87: Sabemos que não podemos nus alto medicar sozinhos , mas quando alguém do turno está com algum tipo de dor ou desconforto, sempre solicitamos um colega quando não se tem o próprio medicamento, e quase sempre é dor de estômago ou analgésico, poderia alinhar com a coordenação algum tipo de instrução . Faz falta esse suporte ao turno. Giovanna - 18/12: Alice, poderia verificar o encaminhamento dessa sugestão? | E87: Angela Santos | F87: Pequena mudança local | G87: Safety - Health | H87: 45631.973 | I87: 04. EMPACOTAMENTO | J87: 46206.452 | K87: Alice Santos | L87: APROVADORES DE IDEIAS | N87: Resolvido | O87: =_xlfn.XLOOKUP(TAB.IDEIAS.TOTAL[[#This Row],[Enviado por]],'BASE DMOS'!A:A,'BASE DMOS'!C:C,"Não encontrado") -> OPERAÇÃO
A88: FB0091319 | B88: suporte para big bag | C88: Em andamento | D88: Solicitamos uma análise de criação de suporte para pendurar o big bag em casos de retirada de café do torrador 3. A forma que tem feito é: tira o café em um carrinho baixo pequeno depois passa para os carrinho grande e depois leva para o suporte fixo já existente perto das fabrimas para ganhar tempo é viável um suporte móvel nesse ponto. De preferência montar e desmontar para não ocupar espaço | E88: Julho Silva | F88: Pequena mudança local | G88: Organisation of work | H88: 45632.485 | I88: 02. TORREFAÇÃO | J88: 45827.395 | K88: Moises Costa | L88: IDEIAS-PROCESSOS | N88: Aguardando Execução | O88: =_xlfn.XLOOKUP(TAB.IDEIAS.TOTAL[[#This Row],[Enviado por]],'BASE DMOS'!A:A,'BASE DMOS'!C:C,"Não encontrado") -> OPERAÇÃO
A89: FB0091938 | B89: Criar procedimento para ajustar o tamanho do fardo | C89: Em andamento | D89: Criar procedimento para ajustar o tamanho do fardo raumak | E89: Relton Moraes | F89: Pequena mudança local | G89: Processo | H89: 45638.411 | I89: 04. EMPACOTAMENTO | J89: 45919.569 | K89: Relton Moraes | L89: APROVADORES DE IDEIAS | N89: Aguardando Aprovação de CAPEX | O89: =_xlfn.XLOOKUP(TAB.IDEIAS.TOTAL[[#This Row],[Enviado por]],'BASE DMOS'!A:A,'BASE DMOS'!C:C,"Não encontrado") -> ADM/TÉCNICO/ASSISTENTE/ESTAG.
A90: FB0091939 | B90: Criar procedimento retirar os fardos mal formados de dentro do robô | C90: Em andamento | D90: Criar procedimento retirar os fardos mal formados de dentro do robô | E90: Relton Moraes | F90: Pequena mudança local | G90: Processo | H90: 45638.413 | I90: 06. PALETIZADORAS DE FARDOS | J90: 45644.645 | K90: Relton Moraes | L90: APROVADORES DE IDEIAS | N90: Aguardando Execução | O90: =_xlfn.XLOOKUP(TAB.IDEIAS.TOTAL[[#This Row],[Enviado por]],'BASE DMOS'!A:A,'BASE DMOS'!C:C,"Não encontrado") -> ADM/TÉCNICO/ASSISTENTE/ESTAG.
A91: FB0091943 | B91: Criar procedimento de troca de bobina raumak | C91: Fechado | D91: Criar procedimento de troca de bobina raumak | E91: Relton Moraes | F91: Pequena mudança local | G91: Processo | H91: 45638.415 | I91: 04. EMPACOTAMENTO | J91: 45919.571 | K91: Relton Moraes | L91: APROVADORES DE IDEIAS | M91: 45919.571 | N91: Fechado | O91: =_xlfn.XLOOKUP(TAB.IDEIAS.TOTAL[[#This Row],[Enviado por]],'BASE DMOS'!A:A,'BASE DMOS'!C:C,"Não encontrado") -> ADM/TÉCNICO/ASSISTENTE/ESTAG.
A92: FB0091975 | B92: Melhoria no procedimento de troca de bobina | C92: Em andamento | D92: no procedimento diz para o operador assim que trocar a bobina passar o filme com cafè porem nem sempre se possivel fazer dessa forma, devido a falha que pode gerar na fotocelula IT-09-211 | E92: Relton Moraes | F92: Pequena mudança local | G92: Processo | H92: 45638.494 | I92: 04. EMPACOTAMENTO | J92: 45810.633 | K92: Relton Moraes | L92: APROVADORES DE IDEIAS | N92: Aguardando Execução | O92: =_xlfn.XLOOKUP(TAB.IDEIAS.TOTAL[[#This Row],[Enviado por]],'BASE DMOS'!A:A,'BASE DMOS'!C:C,"Não encontrado") -> ADM/TÉCNICO/ASSISTENTE/ESTAG.
A93: FB0092008 | B93: montar um quadro onde conseguimos acompanhar os BOS e as etiquetas de SHE | C93: Cancelado | D93: A ideia é colocar esse quadro no lado de fora do contêiner da moagem do lado da porta, onde podemos estar acompanhando o fluxo das etiquetas de SHE e os BOS, faríamos ele por turno pra não ficar tudo junto e sabermos qual turno está menos engajado Assim o pessoal ficaria mais atento pra não deixar de fazer e poderiam ajudar a lembra as pessoas que esqueceram de fazer Nele poderias colocar o nome o turno dos associados, assim cada turno se organizar pra fazer e não esquecer Aline: O ideal seria liberar nos tablets o acesso para verificação dessa informação direto pelo DMOS, liberando acesso a criar listas personalizadas, de acordo com a necessidade de cada área. | E93: Alex Teixeira | F93: Pequena mudança local | G93: Organisation of work | H93: 45638.759 | I93: 06. ADMINISTRATIVO | J93: 45825.631 | L93: IDEIAS-ADMINISTRATIVO | M93: 45825.631 | N93: Cancelado | O93: =_xlfn.XLOOKUP(TAB.IDEIAS.TOTAL[[#This Row],[Enviado por]],'BASE DMOS'!A:A,'BASE DMOS'!C:C,"Não encontrado") -> OPERAÇÃO
A94: FB0092210 | B94: Rodo de 1M (cabo) para limpeza torrador 3 | C94: Resolvido | D94: Confeccionar rodo com cabo de 1M para limpeza do esfriador do torrador 3. chapa de 38cm(largura) X 18cm (altura) (igual a existente no café cru) Confeccionar suporte para armazenamento Pedro Ferreira: é necessário solicitar a orçamento para Padrimax. O material deve ser de tubo galvanizado. | E94: Nilton F Costa | F94: Pequena mudança local | G94: Safety - Health | H94: 45640.39 | I94: 03. TORRADOR 03 | J94: 46164.579 | K94: Pedro Ferreira | L94: IDEIAS-PROCESSOS | N94: Resolvido | O94: =_xlfn.XLOOKUP(TAB.IDEIAS.TOTAL[[#This Row],[Enviado por]],'BASE DMOS'!A:A,'BASE DMOS'!C:C,"Não encontrado") -> OPERAÇÃO
A95: FB0092211 | B95: suporte para calha de recebimento de café cru | C95: Fechado | D95: Titular: Nilton Ferreira fazer suporte para manter a calha na vertical de forma organizada, reduzindo o risco de segurança na área. Hiago solicitar orçamento ao paulinho | E95: Nilton F Costa | F95: Pequena mudança local | G95: Safety - Health | H95: 45640.393 | I95: 05. MOEGAS | J95: 45861.308 | L95: IDEIAS-CAFÉ CRÚ | M95: 45861.308 | N95: Fechado | O95: =_xlfn.XLOOKUP(TAB.IDEIAS.TOTAL[[#This Row],[Enviado por]],'BASE DMOS'!A:A,'BASE DMOS'!C:C,"Não encontrado") -> OPERAÇÃO
A96: FB0092212 | B96: escada para entrada e saída da carreta | C96: Em andamento | D96: Titular: Nilton Ferreira fazer ou comprar uma escada de alumínio (tipo escada de piscina) para entrada e saida na carreta de café cru. Item levantado na auditoria de SHE e avaliado risco ergonômico. SHE: Foi feito a compra da escada e iremos implementa-la | E96: Nilton F Costa | F96: Pequena mudança local | G96: Safety - Health | H96: 45640.401 | I96: 05. MOEGAS | J96: 46128.65 | K96: Guilherme Oliveira | L96: IDEIAS-CAFÉ CRÚ | N96: Aguardando Execução | O96: =_xlfn.XLOOKUP(TAB.IDEIAS.TOTAL[[#This Row],[Enviado por]],'BASE DMOS'!A:A,'BASE DMOS'!C:C,"Não encontrado") -> OPERAÇÃO
A97: FB0092461 | B97: colocar uma plataforma na balança B2.3 e B2.4 | C97: Resolvido | D97: E realizado limpeza nas balanças B2.3 e B2.4 de transporte de café torrado, no local é difícil de colocar escada e tem muita estrutura de ferro pode acontecer acidente. Se colocar uma plataforma como foi realizado do coletor de amostra do torrador 1 fazer o mesmo nas balanças B2.3 e B2.4°. | E97: Edvan Santos | F97: Pequena mudança local | G97: Safety - Health | H97: 45643.267 | I97: 01. TORRADORES | J97: 46162.666 | K97: Ana Martins | L97: IDEIAS-PROCESSOS | N97: Resolvido | O97: =_xlfn.XLOOKUP(TAB.IDEIAS.TOTAL[[#This Row],[Enviado por]],'BASE DMOS'!A:A,'BASE DMOS'!C:C,"Não encontrado") -> OPERAÇÃO
A98: FB0092502 | B98: melhoria na rosca densadora para impacto de densidade | C98: Cancelado | D98: Alteração na faixa de amperagem para aumentar o ajuste operacional e reduzir desarme da rosca (melhoria já implementada). Time: Alexandre Oliveira, Jader, Igor Souza, Marcão, Romero e Andyson | E98: Alexandre Oliveira | F98: Pequena mudança local | G98: Product | H98: 45643.424 | I98: 03. MOAGEM | J98: 45797.471 | L98: IDEIAS-PROCESSOS | M98: 45797.471 | N98: Cancelado | O98: =_xlfn.XLOOKUP(TAB.IDEIAS.TOTAL[[#This Row],[Enviado por]],'BASE DMOS'!A:A,'BASE DMOS'!C:C,"Não encontrado") -> ADM/TÉCNICO/ASSISTENTE/ESTAG.
A99: FB0094453 | B99: Instalação de jabra/microfone na sala Piumhi | C99: Fechado | D99: Para conectar remoto em reuniões que acontecem na sala Piumhi (por exemplo OPS2) é conectado jabra. No entanto, o mesmo não possui boa captação de audio de todos presentes na sala, assim a interação remota na OPS 2 fica prejudicada. Sugestão é instalar um sistema de microfone e, se possível, junto à TV específico para conexão em reuniões. | F99: Pequena mudança local | G99: Organisation of work | H99: 45664.387 | I99: 09.20 SALA DE REUNIÃO | J99: 45861.56 | K99: Ana Pereira | L99: IDEIAS-ADMINISTRATIVO | M99: 45861.56 | N99: Fechado | O99: =_xlfn.XLOOKUP(TAB.IDEIAS.TOTAL[[#This Row],[Enviado por]],'BASE DMOS'!A:A,'BASE DMOS'!C:C,"Não encontrado") -> 0
A100: FB0095351 | B100: barra da estrutura dos moinhos 1 ao 6 | C100: Cancelado | D100: Risco de bater a cabeça, Elaborar Junto com a galera de she se conseguimos fazer uma melhoria nela, como subi ela mais pra cima, fazer uma barra a mais e colocar uma cruzada com a outra tipo um X ou retirar ela mesmo, deixar sem em todos as estruturas dos moinhos. SHE: precisamos da avaliação estrutural para seguirmos com a autorização da remoção. Não temos o desenho técnico e nem laudo estrutural. O objetivo é saber se remover essa estrutura iremos comprometer todo o conjunto. Gentileza direcionar para engenharia. Pedro Ferreira: Do ponto de vista da Engenharia, é necessário elaborar um laudo estrutural da viga, e se através desse, comprova a possiblidade de retirada da viga, entretanto, o valor deste laudo é alto. Será necessário pedir orçamento com a UNIQUE. Assim, Rubens ficará responsável em solicitar orçamento. | E100: Alex Teixeira | F100: Pequena mudança local | G100: Safety - Health | H100: 45671.727 | I100: 09.19 SALA DE PRODUTOS QUÍMICOS | J100: 46098.657 | L100: IDEIAS-SHE | M100: 46098.657 | N100: Cancelado | O100: =_xlfn.XLOOKUP(TAB.IDEIAS.TOTAL[[#This Row],[Enviado por]],'BASE DMOS'!A:A,'BASE DMOS'!C:C,"Não encontrado") -> OPERAÇÃO
...

Sheet % Operação x adm
A1: Meses (Criada) | B1: (Vários itens)
A2: Anos (Criada) | B2: 2026
B4: Rótulos de Coluna
B5: ADM/TÉCNICO/ASSISTENTE/ESTAG. | C5: OPERAÇÃO | D5: Total Geral
A6: Contagem de Enviado por | B6: 92 | C6: 92 | D6: 184
A8: ADM/TÉCNICO/ASSISTENTE/ESTAG. | B8: 50
A9: OPERAÇÃO | B9: 95
C11: Mais de 50% das ideias criadas por Operação

Sheet Taxa de Implementação
A3: Aprovadas | B3: Canceladas/ Rascunho
A4: 58 | B4: 55
B5: 2025-2026 ATUALIZADAS | E5: SÓ 2026
B6: Ideias Implementadas | C6: Ideias Aprovadas | E6: Ideias Implementadas | F6: Ideias Aprovadas
B7: 103 | C7: 181 | E7: 36 | F7: 82
B8: Implementadas/total de ideias aprovadas | C8: =B7/C7 -> 0.56906077 | E8: Implementadas/total de ideias aprovadas | F8: =E7/F7 -> 0.43902439
A11: Nivel 2 | B11: Precisamos mais que 50% de ideias implementadas/executadas
A12: Nivel 3 | B12: Precisamos mais que 80% de ideias implementadas/executadas

Sheet Ideias por categorias
A1: Anos (Criada) | B1: 2026
A3: Contagem de Sub categoria | B3: Rótulos de Coluna
A4: Rótulos de Linha | B4: INVALUABLE | C4: IN PROGRESS | D4: CLOSED | E4: REALIZED | F4: Total Geral
A5: Cost (GE, rework) | B5: 3 | C5: 10 | D5: 1 | E5: 6 | F5: 20
A6: Energy efficiency | D6: 1 | F6: 1
A7: Meio Ambiente | E7: 1 | F7: 1
A8: Organisation of work | B8: 8 | C8: 15 | D8: 1 | E8: 14 | F8: 38
A9: Processo | B9: 5 | C9: 7 | D9: 2 | E9: 10 | F9: 24
A10: Product | B10: 1 | C10: 1 | E10: 1 | F10: 3
A11: Qualidade | B11: 3 | C11: 7 | E11: 5 | F11: 15
A12: Safety - Health | B12: 9 | C12: 11 | D12: 1 | E12: 6 | F12: 27
A13: Yeld | C13: 2 | E13: 1 | F13: 3
A14: New software | E14: 2 | F14: 2
A15: Total Geral | B15: 29 | C15: 53 | D15: 6 | E15: 46 | F15: 134
A17: Rótulos de Linha | B17: INVALUABLE | C17: IN PROGRESS | D17: REALIZED
A18: Cost (GE, rework) | B18: 3 | C18: 8 | D18: 7
A19: Meio Ambiente | D19: 2
A20: Organisation of work | B20: 4 | C20: 10 | D20: 7
A21: Processo | B21: 5 | C21: 7 | D21: 10
A22: Product | B22: 1 | C22: 1 | D22: 1
A23: Qualidade | B23: 2 | C23: 8 | D23: 4
A24: Safety - Health | B24: 8 | C24: 10 | D24: 4
A25: Yeld | C25: 2 | D25: 1

Sheet Ideias por associado
A2: Criada | B2: (Tudo) | D2: Associado que criaram ideia | E2: Assosciados que não criaram ideias | F2: Total FTE | G2: Total ideias criadas | H2: % de ideias por FTE
C3: FTE faltantes | D3: 56 | E3: =F3-D3 -> 66 | F3: 122 | G3: 136 | H3: =G3/F3 -> 1.1147541
A4: Rótulos de Linha | B4: Contagem de Status | C4: Alex Wilson Jose Bernardes
A5: Alex Teixeira | B5: 1 | C5: Alexandre Da Costa Araujo
A6: Aline Fernandes | B6: 9 | C6: Ana Luisa Figueiredo Silva
A7: Ana Martins | B7: 1 | C7: Ana Luiza Paula
A8: Ana Pereira | B8: 1 | C8: Ana Maria da Silva
A9: Angela Santos | B9: 5 | C9: Andre Campos
A10: Bianca Silva | B10: 4 | C10: Bruna Santos
A11: Camila Silva | B11: 1 | C11: Caio Ferreira
A12: Daniela Alves | B12: 1 | C12: Caluan Guimaraes
A13: Edvaldo Silva | B13: 3 | C13: Camila Brasilia
A14: Emilly Silva | B14: 3 | C14: Camila Franco
A15: Fabio S Santos | B15: 8 | C15: Carlos Souza
A16: Fabricio Brant | B16: 7 | C16: Daniel Madureira | H16: Nível 3 | I16: Precisamos de 0,3 de ideias criadas por 1FTE
A17: Giovanna Biffaratte | B17: 6 | C17: Daniel Seri
A18: Isaias Macedo | B18: 1 | C18: DEIVISON SOUZA ALVES CHAVES
A19: Jhonnathan Pereira | B19: 1 | C19: Deusmira Lima
A20: Joelma Inone | B20: 3 | C20: Deyvidson Dos Santos
A21: Karina Silva | B21: 2 | C21: Ednaldo L Silva | D21: Nível 2 | E21: Precisamos de 50% de FTE tenha criado pelo menos 1 ideia
A22: Lucas Vaz | B22: 1 | C22: Eduardo Candido | D22: Nível 3 | E22: Precisamos de 70% de FTE tenha criado pelo menos 1 ideia
A23: Luiz H Silva | B23: 2 | C23: Eduardo Santos
A24: Luzia Rodrigues | B24: 1 | C24: Edvan Santos
A25: Michelle Faria | B25: 3 | C25: EVANIO SANTOS
A26: Moises Costa | B26: 5 | C26: Fabio A Oliveira
A27: Nilton F Costa | B27: 1 | C27: FABIO COELHO
A28: Patrick Pessoa | B28: 3 | C28: Fabrizia Soares
A29: Rafael Santos | B29: 3 | C29: Felipe Simoes
A30: Romilda Cunha | B30: 5 | C30: Gian Silva
A31: Ruth Ribeiro | B31: 4 | C31: Gilberto Rodrigues de Melo
A32: Sara Lobato | B32: 1 | C32: Guilherme P Silva
A33: Thais Souza | B33: 4 | C33: Gustavo Rodrigues
A34: Tiago Carvalho | B34: 3 | C34: Henrique Cardoso
... A62: Total Geral | B62: 184 | C62: Tais Costa
C63: Talita Campos
C64: Thaissa Oliveira
C65: Vicente P Silva
C66: Vilbert Santos
C67: Vinicius de Moraes
C68: Vitor Xavier
C69: Wallace Pereira
C70: Wesley J Silva

Sheet Ideias-area
A1: Anos (Criada) | B1: 2026
A2: Meses (Criada) | B2: (Vários itens) | L2: CAFÉ CRU | M2: 9
L3: JDE CAFES DO BRASIL UNIDADE PIUMHI | M3: 9
A4: Rótulos de Linha | B4: Contagem de Área de trabalho | L4: TORRADORES | M4: 12
A5: 01. CAFÉ CRU | B5: 9 | L5: MOAGEM | M5: 8
A6: 01. JDE CAFES DO BRASIL UNIDADE PIUMHI | B6: 19 | L6: EMPACOTAMENTO | M6: 70
A7: 01. LINHA 01 | B7: 28 | L7: ADMINISTRATIVO | M7: 22
A8: 01. TORRADORES | B8: 5 | L8: LOGISTICA | M8: 1
A9: 02. LINHA 02 | B9: 9 | L9: SALA DE PRODUTOS QUÍMICOS | M9: 13
A10: 02. TORREFAÇÃO | B10: 9
A11: 03. CABLEVEY | B11: 2
A12: 03. MOAGEM | B12: 5
A13: 04. EMPACOTAMENTO | B13: 27
A14: 04. LINHA 04 | B14: 10
A15: 05. LINHA 05 | B15: 8
A16: 06. ADMINISTRATIVO | B16: 18
A17: 06. PALETIZADORAS DE FARDOS | B17: 1
A18: 08. BIOMASSA | B18: 2
A19: 08. LOGISTICA | B19: 3
A20: 09.10 Escritórios administrativos | B20: 7
A21: 09.17 REFEITÓRIO | B21: 2
... A28: 07. AREAS EXTERNAS | B28: 2
A29: Total Geral | B29: 184 | L29: CAFÉ CRU | M29: 21
L30: JDE CAFES DO BRASIL UNIDADE PIUMHI | M30: 27
L31: TORRADORES | M31: 28
L32: MOAGEM | M32: 21
L33: EMPACOTAMENTO | M33: 174
L34: ADMINISTRATIVO | M34: 28
L35: LOGISTICA | M35: 10
L36: SALA DE PRODUTOS QUÍMICOS | M36: 16

Sheet CADASTRO
A1: NOME | B1: TURNO COMP | C1: TURNO | D1: COORDENADOR | E1: FUNÇÃO | F1: STATUS | G1: ÁREA | H1: IDFIXO
A2: ABNER BARROS DE PAIVA | B2: 3º turno - 6x1 - 22:00 ás | C2: 3 | D2: LEONARDO ANTONIO FRANCELINO JUNIOR | E2: OPERADOR INDUSTRIAL I | F2: ATIVO | G2: FABRIMA | H2: 191
A3: ALEX BARBARA | B3: 1º Turno - 6x2 06:00 - 14 | C3: 1 | D3: HENRIQUE MARTINS CARDOSO | E3: TECNICO MECANICO II | F3: ATIVO | G3: MANUTENÇÃO | H3: 188
A4: ALEX SANDRO ALVES TEIXEIRA | B4: 2º turno - 6x1 - 14:00 ás | C4: 2 | D4: MICHELLE APARECIDA FARIA | E4: OPERADOR INDUSTRIAL II | F4: ATIVO | G4: MOINHO | H4: 190
A5: ALEXANDRE BATISTA DE OLIVEIRA | B5: 1º Turno - 6x2 06:00 - 14 | C5: 1 | D5: HENRIQUE MARTINS CARDOSO | E5: TECNICO MECANICO III | F5: ATIVO | G5: MANUTENÇÃO | H5: 192
A6: ALEXANDRE DE ASSIS DA COSTA | B6: 3º Turno - 6x2 22:00 - 06 | C6: 3 | D6: HENRIQUE MARTINS CARDOSO | E6: TECNICO MECANICO II | F6: ATIVO | G6: MANUTENÇÃO | H6: 205
A7: ALICE RAMOS MORAIS | B7: 0- ADM- SEG/SEX 08:30 ÀS | C7: 0 | D7: CAIO GUILHERME SALES FERREIRA | E7: ANALISTA GESTAO QUALIDADE PL | F7: ATIVO | G7: QUALIDADE | H7: 194
A8: ALINE FERNANDES | B8: 0 - ADM - SEG / SEX 08:00 | C8: 0 | D8: SARAH FELICIO TEIXEIRA | E8: ASSISTENTE ADMINISTRATIVO | F8: ATIVO | G8: ALMOXARIFADO | H8: 195
A9: ANA BEATRIZ LIMA SILVA | B9: 0 - ADM - SEG/SEX 08:30 A | C9: 0 | D9: CAIO GUILHERME SALES FERREIRA | E9: ESTAGIARIO | F9: ATIVO | G9: QUALIDADE | H9: 309
A10: ANA CAROLLINE SIQUEIRA MARTINS | B10: 0- ADM- SEG/SEX 08:30 ÀS | C10: 0 | D10: ELIEZER SILVA | E10: ASSISTENTE ADMINISTRATIVO | F10: ATIVO | G10: MANUTENÇÃO ADM | H10: 196
A11: ANA JULIA COSTA SILVA | B11: 2º turno - 6x1 - 14:00 ás | C11: 2 | D11: IZABELA CAROLINE PUGLIESI | E11: OPERADOR INDUSTRIAL I | F11: ATIVO | G11: FABRIMA | H11: 197
A12: ANA LUISA FIGUEIREDO SILVA | B12: HIRE NOW | C12: H | D12: ELIEZER SILVA | E12: ASSISTENTE ADMINISTRATIVO | F12: ATIVO | G12: MANUTENÇÃO ADM | H12: 198
A13: ANA LUISA SOARES PEREIRA | B13: 0 - ADM - SEG / SEX 08:00 | C13: 0 | D13: DANIEL SERI | E13: ANALISTA FACILITIES | F13: ATIVO | G13: FACILITIES | H13: 199
... A122: WILGNER REBERTE TAYLON DA SILVA | B122: 2º turno - 6x1 - 14:00 ás | C122: 2 | D122: IZABELA CAROLINE PUGLIESI | E122: AUXILIAR INDUSTRIAL | F122: ATIVO | G122: FABRIMA | H122: 307

Sheet BASE DMOS
A1: Base DMOS | B1: NOME | C1: TIPO | D1: CARGO | E1: AREA | F1: COORDENADOR | G1: SITUAÇÃO
A2: Angela Santos | B2: ANGELA ALVES DOS SANTOS | C2: OPERAÇÃO | D2: OPERADOR INDUSTRIAL II | E2: EMPACOTAMENTO | F2: RELTON FERREIRA DE MORAES | G2: ATIVO
A3: Alex Barbara | B3: ALEX BARBARA | C3: ADM/TÉCNICO/ASSISTENTE/ESTAG. | D3: TECNICO MECANICO II | E3: MANUTENÇÃO | F3: HENRIQUE MARTINS CARDOSO | G3: ATIVO
A4: Carlos Souza | B4: CARLOS INACIO PEREIRA DE SOUZA | C4: OPERAÇÃO | D4: OPERADOR INDUSTRIAL I | E4: EMPACOTAMENTO | F4: LEONARDO ANTONIO FRANCELINO JUNIOR | G4: ATIVO
A5: Alex Wilson Jose Bernardes | B5: ALEX WILSON JOSE BERNARDES | C5: OPERAÇÃO | D5: OPERADOR LOGISTICO I | E5: LOGÍSTICA | F5: FABIO ASSIS DE OLIVEIRA | G5: DESLIGADO
A6: Alexandre Oliveira | B6: ALEXANDRE BATISTA DE OLIVEIRA | C6: ADM/TÉCNICO/ASSISTENTE/ESTAG. | D6: TECNICO MECANICO III | E6: MANUTENÇÃO | F6: HENRIQUE MARTINS CARDOSO | G6: ATIVO
A7: Alexandre Da Costa Araujo | B7: ALEXANDRE DE ASSIS DA COSTA | C7: ADM/TÉCNICO/ASSISTENTE/ESTAG. | D7: TECNICO MECANICO II | E7: MANUTENÇÃO | F7: HENRIQUE MARTINS CARDOSO | G7: ATIVO
A8: Alice Morais | B8: ALICE RAMOS MORAIS | C8: ADM/TÉCNICO/ASSISTENTE/ESTAG. | D8: ANALISTA GESTAO QUALIDADE PL | E8: QUALIDADE | F8: COORDENADOR DE QUALIDADE | G8: ATIVO
A9: Aline Fernandes | B9: ALINE FERNANDES | C9: ADM/TÉCNICO/ASSISTENTE/ESTAG. | D9: ASSISTENTE ADMINISTRATIVO | E9: ALMOXARIFADO | F9: SARAH FELICIO TEIXEIRA | G9: ATIVO
A10: Ana Martins | B10: ANA CAROLLINE SIQUEIRA MARTINS | C10: ADM/TÉCNICO/ASSISTENTE/ESTAG. | D10: ASSISTENTE ADMINISTRATIVO | E10: MANUTENÇÃO | F10: ELIEZER SILVA | G10: ATIVO
A11: Daniel Madureira | B11: DANIEL ALMEIDA MADUREIRA | C11: OPERAÇÃO | D11: OPERADOR INDUSTRIAL II | E11: MOAGEM | F11: MICHELLE APARECIDA FARIA | G11: ATIVO
A12: Ana Luisa Figueiredo Silva | B12: ANA LUISA FIGUEIREDO SILVA | C12: ADM/TÉCNICO/ASSISTENTE/ESTAG. | D12: ASSISTENTE ADMINISTRATIVO | E12: MANUTENÇÃO | F12: ELIEZER SILVA | G12: ATIVO
... A157: Leandro Freire | B157: LEANDRO DE PAULA FREIRE | C157: ADM/TÉCNICO/ASSISTENTE/ESTAG. | D157: ANALISTA MANUTENCAO JR | E157: MANUTENÇÃO ADM | F157: ELIEZER SILVA | G157: DESLIGADO
